Workbook

Sheet 📖 Как пользоваться
B1: SADI · Инструкция пользователя · Вектор развития консалтинга
B2: Скоринговая модель · 19 отраслей · данные 2015–2024 · горизонт до 2034 · Технологии Доверия
B4: 🎯 Что такое SADI? | C4: Industry Analytics Demand Index - взвешенная сумма нормализованных оценок по 9 критериям в 4 блоках. Формула: SADI = 0.35×B1 + 0.20×B2 + 0.30×B3 + 0.15×B4 Чем выше SADI - тем выше потенциал отрасли.
B11: 📊 4 блока критериев | C11: B1 - Экономика (35%): доля ВВП, индекс производства, инвестиции, численность B2 - Процессы (20%): зарплата, производительность труда B3 - Цифровизация (30%): рентабельность продаж, рост производства B4 - Регуляторика (15%): налоговая нагрузка, доля убыточных организаций
B18: 🗂️ Структура файла | C18: Расчет - служебный лист (не редактировать!) 📖 Как пользоваться - эта страница Рейтинг и прогноз - ГЛАВНЫЙ лист: выберите сценарий (E6) и отрасль (J6) ➕ Мои критерии - добавьте до 5 собственных критериев 🏆 Итог+ - расширенный рейтинг с вашими критериями 📂 Данные - исходный датасет 2015-2024
B25: 🔧 Как работать | C25: 1. Откройте лист «Рейтинг и прогноз» 2. Ячейка E6 - нажмите и выберите сценарий из выпадающего списка 3. Ячейка J6 - нажмите и выберите отрасль из выпадающего списка 4. Рейтинг и профиль справа обновятся автоматически Сценарии: • Базовый (B1=35% B2=20% B3=30% B4=15%) • Экономический (B1=50%) • Технологический (B3=55%) • Регуляторный (B4=25%)
B32: ➕ Мои критерии | C32: Лист «➕ Мои критерии»: · Строка 6 - введите название критерия и вес (%) · Строки 8–26 - оценки 1–5 для каждой отрасли · Нормализация считается автоматически · Суммарный вес не более 30% · Результат → лист «🏆 Итог+»
B39: ✅ Приоритеты | C39: A - SADI ≥ 0.55 → безусловный приоритет B - SADI 0.40–0.54 → перспективная ниша C - SADI < 0.40 → нишевый приоритет

Sheet Рейтинг и прогноз
B1: SADI · Скоринговая модель · Вектор развития консалтинга · Технологии Доверия
D4: 📊 РЕЙТИНГ ОТРАСЛЕЙ · прогноз на 3 / 5 / 10 лет | I4: 🔍 ПРОФИЛЬ ОТРАСЛИ
D5: ⚙️ Управление моделью
D6: Сценарий: | E6: Регуляторный (Б4=25%) | F6: ← из списка | I6: Выберите отрасль: | J6: Оборонно-промышленный комплекс
D7: Веса блоков: | E7: =IF(E6="Экономический (Б1=50%)","Б1=50% · Б2=15% · Б3=25% · Б4=10%",IF(E6="Технологический (Б3=55%)","Б1=20% · Б2=15% · Б3=55% · Б4=10%",IF(E6="Регуляторный (Б4=25%)","Б1=25% · Б2=20% · Б3=30% · Б4=25%","Б1=35% · Б2=20% · Б3=30% · Б4=15%"))) -> Б1=25% · Б2=20% · Б3=30% · Б4=25% | I7: Сценарий профиля: | J7: =E6 -> Регуляторный (Б4=25%)
B9: # | D9: Отрасль | E9: 3 года (2027) | F9: 5 лет (2029) | G9: 10 лет (2034) | I9: =IF(J6="","— выберите отрасль —",J6) -> Оборонно-промышленный комплекс
B10: 1 | D10: Оборонно-промышленный комплекс | E10: =IFERROR(IF($E$6="Экономический (Б1=50%)",VLOOKUP(D10,'Расчет'!$A$2:$AA$20,14,0),IF($E$6="Технологический (Б3=55%)",VLOOKUP(D10,'Расчет'!$A$2:$AA$20,19,0),IF($E$6="Регуляторный (Б4=25%)",VLOOKUP(D10,'Расчет'!$A$2:$AA$20,24,0),VLOOKUP(D10,'Расчет'!$A$2:$AA$20,3,0)))),"") -> 0.4733 | F10: =IFERROR(IF($E$6="Экономический (Б1=50%)",VLOOKUP(D10,'Расчет'!$A$2:$AA$20,15,0),IF($E$6="Технологический (Б3=55%)",VLOOKUP(D10,'Расчет'!$A$2:$AA$20,20,0),IF($E$6="Регуляторный (Б4=25%)",VLOOKUP(D10,'Расчет'!$A$2:$AA$20,25,0),VLOOKUP(D10,'Расчет'!$A$2:$AA$20,4,0)))),"") -> 0.4724 | G10: =IFERROR(IF($E$6="Экономический (Б1=50%)",VLOOKUP(D10,'Расчет'!$A$2:$AA$20,16,0),IF($E$6="Технологический (Б3=55%)",VLOOKUP(D10,'Расчет'!$A$2:$AA$20,21,0),IF($E$6="Регуляторный (Б4=25%)",VLOOKUP(D10,'Расчет'!$A$2:$AA$20,26,0),VLOOKUP(D10,'Расчет'!$A$2:$AA$20,5,0)))),"") -> 0.4701 | I10: SADI 2024 (база): | J10: =IFERROR(VLOOKUP($J$6,'Расчет'!$A$2:$AA$20,2,0),"") -> 0.4655 | L10: =IFERROR(VLOOKUP($J$6,'Расчет'!$A$2:$AA$20,2,0),"") -> 0.4655
B11: 2 | D11: Нефтегазовый комплекс | E11: =IFERROR(IF($E$6="Экономический (Б1=50%)",VLOOKUP(D11,'Расчет'!$A$2:$AA$20,14,0),IF($E$6="Технологический (Б3=55%)",VLOOKUP(D11,'Расчет'!$A$2:$AA$20,19,0),IF($E$6="Регуляторный (Б4=25%)",VLOOKUP(D11,'Расчет'!$A$2:$AA$20,24,0),VLOOKUP(D11,'Расчет'!$A$2:$AA$20,3,0)))),"") -> 0.4464 | F11: =IFERROR(IF($E$6="Экономический (Б1=50%)",VLOOKUP(D11,'Расчет'!$A$2:$AA$20,15,0),IF($E$6="Технологический (Б3=55%)",VLOOKUP(D11,'Расчет'!$A$2:$AA$20,20,0),IF($E$6="Регуляторный (Б4=25%)",VLOOKUP(D11,'Расчет'!$A$2:$AA$20,25,0),VLOOKUP(D11,'Расчет'!$A$2:$AA$20,4,0)))),"") -> 0.4476 | G11: =IFERROR(IF($E$6="Экономический (Б1=50%)",VLOOKUP(D11,'Расчет'!$A$2:$AA$20,16,0),IF($E$6="Технологический (Б3=55%)",VLOOKUP(D11,'Расчет'!$A$2:$AA$20,21,0),IF($E$6="Регуляторный (Б4=25%)",VLOOKUP(D11,'Расчет'!$A$2:$AA$20,26,0),VLOOKUP(D11,'Расчет'!$A$2:$AA$20,5,0)))),"") -> 0.4504
B12: 3 | D12: Финансы и страхование | E12: =IFERROR(IF($E$6="Экономический (Б1=50%)",VLOOKUP(D12,'Расчет'!$A$2:$AA$20,14,0),IF($E$6="Технологический (Б3=55%)",VLOOKUP(D12,'Расчет'!$A$2:$AA$20,19,0),IF($E$6="Регуляторный (Б4=25%)",VLOOKUP(D12,'Расчет'!$A$2:$AA$20,24,0),VLOOKUP(D12,'Расчет'!$A$2:$AA$20,3,0)))),"") -> 0.4424 | F12: =IFERROR(IF($E$6="Экономический (Б1=50%)",VLOOKUP(D12,'Расчет'!$A$2:$AA$20,15,0),IF($E$6="Технологический (Б3=55%)",VLOOKUP(D12,'Расчет'!$A$2:$AA$20,20,0),IF($E$6="Регуляторный (Б4=25%)",VLOOKUP(D12,'Расчет'!$A$2:$AA$20,25,0),VLOOKUP(D12,'Расчет'!$A$2:$AA$20,4,0)))),"") -> 0.4431 | G12: =IFERROR(IF($E$6="Экономический (Б1=50%)",VLOOKUP(D12,'Расчет'!$A$2:$AA$20,16,0),IF($E$6="Технологический (Б3=55%)",VLOOKUP(D12,'Расчет'!$A$2:$AA$20,21,0),IF($E$6="Регуляторный (Б4=25%)",VLOOKUP(D12,'Расчет'!$A$2:$AA$20,26,0),VLOOKUP(D12,'Расчет'!$A$2:$AA$20,5,0)))),"") -> 0.4449 | I12: ПРОГНОЗ SADI
B13: 4 | D13: Фармацевтика | E13: =IFERROR(IF($E$6="Экономический (Б1=50%)",VLOOKUP(D13,'Расчет'!$A$2:$AA$20,14,0),IF($E$6="Технологический (Б3=55%)",VLOOKUP(D13,'Расчет'!$A$2:$AA$20,19,0),IF($E$6="Регуляторный (Б4=25%)",VLOOKUP(D13,'Расчет'!$A$2:$AA$20,24,0),VLOOKUP(D13,'Расчет'!$A$2:$AA$20,3,0)))),"") -> 0.4306 | F13: =IFERROR(IF($E$6="Экономический (Б1=50%)",VLOOKUP(D13,'Расчет'!$A$2:$AA$20,15,0),IF($E$6="Технологический (Б3=55%)",VLOOKUP(D13,'Расчет'!$A$2:$AA$20,20,0),IF($E$6="Регуляторный (Б4=25%)",VLOOKUP(D13,'Расчет'!$A$2:$AA$20,25,0),VLOOKUP(D13,'Расчет'!$A$2:$AA$20,4,0)))),"") -> 0.4315 | G13: =IFERROR(IF($E$6="Экономический (Б1=50%)",VLOOKUP(D13,'Расчет'!$A$2:$AA$20,16,0),IF($E$6="Технологический (Б3=55%)",VLOOKUP(D13,'Расчет'!$A$2:$AA$20,21,0),IF($E$6="Регуляторный (Б4=25%)",VLOOKUP(D13,'Расчет'!$A$2:$AA$20,26,0),VLOOKUP(D13,'Расчет'!$A$2:$AA$20,5,0)))),"") -> 0.4338 | I13: 3 года (2027) | J13: =IFERROR(IF($E$6="Экономический (Б1=50%)",VLOOKUP($J$6,'Расчет'!$A$2:$AA$20,14,0),IF($E$6="Технологический (Б3=55%)",VLOOKUP($J$6,'Расчет'!$A$2:$AA$20,19,0),IF($E$6="Регуляторный (Б4=25%)",VLOOKUP($J$6,'Расчет'!$A$2:$AA$20,24,0),VLOOKUP($J$6,'Расчет'!$A$2:$AA$20,3,0)))),"") -> 0.4733 | L13: =IFERROR(IF($E$6="Экономический (Б1=50%)",VLOOKUP($J$6,'Расчет'!$A$2:$AA$20,14,0),IF($E$6="Технологический (Б3=55%)",VLOOKUP($J$6,'Расчет'!$A$2:$AA$20,19,0),IF($E$6="Регуляторный (Б4=25%)",VLOOKUP($J$6,'Расчет'!$A$2:$AA$20,24,0),VLOOKUP($J$6,'Расчет'!$A$2:$AA$20,3,0)))),"") -> 0.4733
B14: 5 | D14: Обрабатывающая промышленность | E14: =IFERROR(IF($E$6="Экономический (Б1=50%)",VLOOKUP(D14,'Расчет'!$A$2:$AA$20,14,0),IF($E$6="Технологический (Б3=55%)",VLOOKUP(D14,'Расчет'!$A$2:$AA$20,19,0),IF($E$6="Регуляторный (Б4=25%)",VLOOKUP(D14,'Расчет'!$A$2:$AA$20,24,0),VLOOKUP(D14,'Расчет'!$A$2:$AA$20,3,0)))),"") -> 0.3441 | F14: =IFERROR(IF($E$6="Экономический (Б1=50%)",VLOOKUP(D14,'Расчет'!$A$2:$AA$20,15,0),IF($E$6="Технологический (Б3=55%)",VLOOKUP(D14,'Расчет'!$A$2:$AA$20,20,0),IF($E$6="Регуляторный (Б4=25%)",VLOOKUP(D14,'Расчет'!$A$2:$AA$20,25,0),VLOOKUP(D14,'Расчет'!$A$2:$AA$20,4,0)))),"") -> 0.3422 | G14: =IFERROR(IF($E$6="Экономический (Б1=50%)",VLOOKUP(D14,'Расчет'!$A$2:$AA$20,16,0),IF($E$6="Технологический (Б3=55%)",VLOOKUP(D14,'Расчет'!$A$2:$AA$20,21,0),IF($E$6="Регуляторный (Б4=25%)",VLOOKUP(D14,'Расчет'!$A$2:$AA$20,26,0),VLOOKUP(D14,'Расчет'!$A$2:$AA$20,5,0)))),"") -> 0.3374 | I14: 5 лет (2029) | J14: =IFERROR(IF($E$6="Экономический (Б1=50%)",VLOOKUP($J$6,'Расчет'!$A$2:$AA$20,15,0),IF($E$6="Технологический (Б3=55%)",VLOOKUP($J$6,'Расчет'!$A$2:$AA$20,20,0),IF($E$6="Регуляторный (Б4=25%)",VLOOKUP($J$6,'Расчет'!$A$2:$AA$20,25,0),VLOOKUP($J$6,'Расчет'!$A$2:$AA$20,4,0)))),"") -> 0.4724 | L14: =IFERROR(IF($E$6="Экономический (Б1=50%)",VLOOKUP($J$6,'Расчет'!$A$2:$AA$20,15,0),IF($E$6="Технологический (Б3=55%)",VLOOKUP($J$6,'Расчет'!$A$2:$AA$20,20,0),IF($E$6="Регуляторный (Б4=25%)",VLOOKUP($J$6,'Расчет'!$A$2:$AA$20,25,0),VLOOKUP($J$6,'Расчет'!$A$2:$AA$20,4,0)))),"") -> 0.4724
B15: 6 | D15: Металлургия | E15: =IFERROR(IF($E$6="Экономический (Б1=50%)",VLOOKUP(D15,'Расчет'!$A$2:$AA$20,14,0),IF($E$6="Технологический (Б3=55%)",VLOOKUP(D15,'Расчет'!$A$2:$AA$20,19,0),IF($E$6="Регуляторный (Б4=25%)",VLOOKUP(D15,'Расчет'!$A$2:$AA$20,24,0),VLOOKUP(D15,'Расчет'!$A$2:$AA$20,3,0)))),"") -> 0.3189 | F15: =IFERROR(IF($E$6="Экономический (Б1=50%)",VLOOKUP(D15,'Расчет'!$A$2:$AA$20,15,0),IF($E$6="Технологический (Б3=55%)",VLOOKUP(D15,'Расчет'!$A$2:$AA$20,20,0),IF($E$6="Регуляторный (Б4=25%)",VLOOKUP(D15,'Расчет'!$A$2:$AA$20,25,0),VLOOKUP(D15,'Расчет'!$A$2:$AA$20,4,0)))),"") -> 0.3129 | G15: =IFERROR(IF($E$6="Экономический (Б1=50%)",VLOOKUP(D15,'Расчет'!$A$2:$AA$20,16,0),IF($E$6="Технологический (Б3=55%)",VLOOKUP(D15,'Расчет'!$A$2:$AA$20,21,0),IF($E$6="Регуляторный (Б4=25%)",VLOOKUP(D15,'Расчет'!$A$2:$AA$20,26,0),VLOOKUP(D15,'Расчет'!$A$2:$AA$20,5,0)))),"") -> 0.2978 | I15: 10 лет (2034) | J15: =IFERROR(IF($E$6="Экономический (Б1=50%)",VLOOKUP($J$6,'Расчет'!$A$2:$AA$20,16,0),IF($E$6="Технологический (Б3=55%)",VLOOKUP($J$6,'Расчет'!$A$2:$AA$20,21,0),IF($E$6="Регуляторный (Б4=25%)",VLOOKUP($J$6,'Расчет'!$A$2:$AA$20,26,0),VLOOKUP($J$6,'Расчет'!$A$2:$AA$20,5,0)))),"") -> 0.4701 | L15: =IFERROR(IF($E$6="Экономический (Б1=50%)",VLOOKUP($J$6,'Расчет'!$A$2:$AA$20,16,0),IF($E$6="Технологический (Б3=55%)",VLOOKUP($J$6,'Расчет'!$A$2:$AA$20,21,0),IF($E$6="Регуляторный (Б4=25%)",VLOOKUP($J$6,'Расчет'!$A$2:$AA$20,26,0),VLOOKUP($J$6,'Расчет'!$A$2:$AA$20,5,0)))),"") -> 0.4701
B16: 7 | D16: Здравоохранение | E16: =IFERROR(IF($E$6="Экономический (Б1=50%)",VLOOKUP(D16,'Расчет'!$A$2:$AA$20,14,0),IF($E$6="Технологический (Б3=55%)",VLOOKUP(D16,'Расчет'!$A$2:$AA$20,19,0),IF($E$6="Регуляторный (Б4=25%)",VLOOKUP(D16,'Расчет'!$A$2:$AA$20,24,0),VLOOKUP(D16,'Расчет'!$A$2:$AA$20,3,0)))),"") -> 0.2933 | F16: =IFERROR(IF($E$6="Экономический (Б1=50%)",VLOOKUP(D16,'Расчет'!$A$2:$AA$20,15,0),IF($E$6="Технологический (Б3=55%)",VLOOKUP(D16,'Расчет'!$A$2:$AA$20,20,0),IF($E$6="Регуляторный (Б4=25%)",VLOOKUP(D16,'Расчет'!$A$2:$AA$20,25,0),VLOOKUP(D16,'Расчет'!$A$2:$AA$20,4,0)))),"") -> 0.2907 | G16: =IFERROR(IF($E$6="Экономический (Б1=50%)",VLOOKUP(D16,'Расчет'!$A$2:$AA$20,16,0),IF($E$6="Технологический (Б3=55%)",VLOOKUP(D16,'Расчет'!$A$2:$AA$20,21,0),IF($E$6="Регуляторный (Б4=25%)",VLOOKUP(D16,'Расчет'!$A$2:$AA$20,26,0),VLOOKUP(D16,'Расчет'!$A$2:$AA$20,5,0)))),"") -> 0.2841
B17: 8 | D17: Торговля | E17: =IFERROR(IF($E$6="Экономический (Б1=50%)",VLOOKUP(D17,'Расчет'!$A$2:$AA$20,14,0),IF($E$6="Технологический (Б3=55%)",VLOOKUP(D17,'Расчет'!$A$2:$AA$20,19,0),IF($E$6="Регуляторный (Б4=25%)",VLOOKUP(D17,'Расчет'!$A$2:$AA$20,24,0),VLOOKUP(D17,'Расчет'!$A$2:$AA$20,3,0)))),"") -> 0.2956 | F17: =IFERROR(IF($E$6="Экономический (Б1=50%)",VLOOKUP(D17,'Расчет'!$A$2:$AA$20,15,0),IF($E$6="Технологический (Б3=55%)",VLOOKUP(D17,'Расчет'!$A$2:$AA$20,20,0),IF($E$6="Регуляторный (Б4=25%)",VLOOKUP(D17,'Расчет'!$A$2:$AA$20,25,0),VLOOKUP(D17,'Расчет'!$A$2:$AA$20,4,0)))),"") -> 0.2944 | G17: =IFERROR(IF($E$6="Экономический (Б1=50%)",VLOOKUP(D17,'Расчет'!$A$2:$AA$20,16,0),IF($E$6="Технологический (Б3=55%)",VLOOKUP(D17,'Расчет'!$A$2:$AA$20,21,0),IF($E$6="Регуляторный (Б4=25%)",VLOOKUP(D17,'Расчет'!$A$2:$AA$20,26,0),VLOOKUP(D17,'Расчет'!$A$2:$AA$20,5,0)))),"") -> 0.2916 | I17: Тренд (наклон/год): | J17: =IFERROR(VLOOKUP($J$6,'Расчет'!$A$2:$AA$20,6,0),"") -> -0.00132 | L17: =IFERROR(VLOOKUP($J$6,'Расчет'!$A$2:$AA$20,12,0),"") -> → Стабильно
B18: 9 | D18: Недвижимость | E18: =IFERROR(IF($E$6="Экономический (Б1=50%)",VLOOKUP(D18,'Расчет'!$A$2:$AA$20,14,0),IF($E$6="Технологический (Б3=55%)",VLOOKUP(D18,'Расчет'!$A$2:$AA$20,19,0),IF($E$6="Регуляторный (Б4=25%)",VLOOKUP(D18,'Расчет'!$A$2:$AA$20,24,0),VLOOKUP(D18,'Расчет'!$A$2:$AA$20,3,0)))),"") -> 0.3086 | F18: =IFERROR(IF($E$6="Экономический (Б1=50%)",VLOOKUP(D18,'Расчет'!$A$2:$AA$20,15,0),IF($E$6="Технологический (Б3=55%)",VLOOKUP(D18,'Расчет'!$A$2:$AA$20,20,0),IF($E$6="Регуляторный (Б4=25%)",VLOOKUP(D18,'Расчет'!$A$2:$AA$20,25,0),VLOOKUP(D18,'Расчет'!$A$2:$AA$20,4,0)))),"") -> 0.3079 | G18: =IFERROR(IF($E$6="Экономический (Б1=50%)",VLOOKUP(D18,'Расчет'!$A$2:$AA$20,16,0),IF($E$6="Технологический (Б3=55%)",VLOOKUP(D18,'Расчет'!$A$2:$AA$20,21,0),IF($E$6="Регуляторный (Б4=25%)",VLOOKUP(D18,'Расчет'!$A$2:$AA$20,26,0),VLOOKUP(D18,'Расчет'!$A$2:$AA$20,5,0)))),"") -> 0.3064
B19: 10 | D19: Медиа и рекламные технологии | E19: =IFERROR(IF($E$6="Экономический (Б1=50%)",VLOOKUP(D19,'Расчет'!$A$2:$AA$20,14,0),IF($E$6="Технологический (Б3=55%)",VLOOKUP(D19,'Расчет'!$A$2:$AA$20,19,0),IF($E$6="Регуляторный (Б4=25%)",VLOOKUP(D19,'Расчет'!$A$2:$AA$20,24,0),VLOOKUP(D19,'Расчет'!$A$2:$AA$20,3,0)))),"") -> 0.3149 | F19: =IFERROR(IF($E$6="Экономический (Б1=50%)",VLOOKUP(D19,'Расчет'!$A$2:$AA$20,15,0),IF($E$6="Технологический (Б3=55%)",VLOOKUP(D19,'Расчет'!$A$2:$AA$20,20,0),IF($E$6="Регуляторный (Б4=25%)",VLOOKUP(D19,'Расчет'!$A$2:$AA$20,25,0),VLOOKUP(D19,'Расчет'!$A$2:$AA$20,4,0)))),"") -> 0.3141 | G19: =IFERROR(IF($E$6="Экономический (Б1=50%)",VLOOKUP(D19,'Расчет'!$A$2:$AA$20,16,0),IF($E$6="Технологический (Б3=55%)",VLOOKUP(D19,'Расчет'!$A$2:$AA$20,21,0),IF($E$6="Регуляторный (Б4=25%)",VLOOKUP(D19,'Расчет'!$A$2:$AA$20,26,0),VLOOKUP(D19,'Расчет'!$A$2:$AA$20,5,0)))),"") -> 0.312 | I19: ОЦЕНКА ПО БЛОКАМ (2024)
B20: 11 | D20: Химическая промышленность | E20: =IFERROR(IF($E$6="Экономический (Б1=50%)",VLOOKUP(D20,'Расчет'!$A$2:$AA$20,14,0),IF($E$6="Технологический (Б3=55%)",VLOOKUP(D20,'Расчет'!$A$2:$AA$20,19,0),IF($E$6="Регуляторный (Б4=25%)",VLOOKUP(D20,'Расчет'!$A$2:$AA$20,24,0),VLOOKUP(D20,'Расчет'!$A$2:$AA$20,3,0)))),"") -> 0.293 | F20: =IFERROR(IF($E$6="Экономический (Б1=50%)",VLOOKUP(D20,'Расчет'!$A$2:$AA$20,15,0),IF($E$6="Технологический (Б3=55%)",VLOOKUP(D20,'Расчет'!$A$2:$AA$20,20,0),IF($E$6="Регуляторный (Б4=25%)",VLOOKUP(D20,'Расчет'!$A$2:$AA$20,25,0),VLOOKUP(D20,'Расчет'!$A$2:$AA$20,4,0)))),"") -> 0.2909 | G20: =IFERROR(IF($E$6="Экономический (Б1=50%)",VLOOKUP(D20,'Расчет'!$A$2:$AA$20,16,0),IF($E$6="Технологический (Б3=55%)",VLOOKUP(D20,'Расчет'!$A$2:$AA$20,21,0),IF($E$6="Регуляторный (Б4=25%)",VLOOKUP(D20,'Расчет'!$A$2:$AA$20,26,0),VLOOKUP(D20,'Расчет'!$A$2:$AA$20,5,0)))),"") -> 0.2855 | I20: Б1 - Экономика | J20: =IFERROR(VLOOKUP($J$6,'Расчет'!$A$2:$AA$20,7,0),"") -> 0.3587 | L20: =IFERROR(REPT("█",ROUND(VLOOKUP($J$6,'Расчет'!$A$2:$AA$20,7,0)*10,0)),"") -> ████
B21: 12 | D21: АПК и пищевая промышленность | E21: =IFERROR(IF($E$6="Экономический (Б1=50%)",VLOOKUP(D21,'Расчет'!$A$2:$AA$20,14,0),IF($E$6="Технологический (Б3=55%)",VLOOKUP(D21,'Расчет'!$A$2:$AA$20,19,0),IF($E$6="Регуляторный (Б4=25%)",VLOOKUP(D21,'Расчет'!$A$2:$AA$20,24,0),VLOOKUP(D21,'Расчет'!$A$2:$AA$20,3,0)))),"") -> 0.2852 | F21: =IFERROR(IF($E$6="Экономический (Б1=50%)",VLOOKUP(D21,'Расчет'!$A$2:$AA$20,15,0),IF($E$6="Технологический (Б3=55%)",VLOOKUP(D21,'Расчет'!$A$2:$AA$20,20,0),IF($E$6="Регуляторный (Б4=25%)",VLOOKUP(D21,'Расчет'!$A$2:$AA$20,25,0),VLOOKUP(D21,'Расчет'!$A$2:$AA$20,4,0)))),"") -> 0.2835 | G21: =IFERROR(IF($E$6="Экономический (Б1=50%)",VLOOKUP(D21,'Расчет'!$A$2:$AA$20,16,0),IF($E$6="Технологический (Б3=55%)",VLOOKUP(D21,'Расчет'!$A$2:$AA$20,21,0),IF($E$6="Регуляторный (Б4=25%)",VLOOKUP(D21,'Расчет'!$A$2:$AA$20,26,0),VLOOKUP(D21,'Расчет'!$A$2:$AA$20,5,0)))),"") -> 0.2793 | I21: Б2 - Процессы | J21: =IFERROR(VLOOKUP($J$6,'Расчет'!$A$2:$AA$20,8,0),"") -> 0.588 | L21: =IFERROR(REPT("█",ROUND(VLOOKUP($J$6,'Расчет'!$A$2:$AA$20,8,0)*10,0)),"") -> ██████
B22: 13 | D22: Туризм и гостеприимство | E22: =IFERROR(IF($E$6="Экономический (Б1=50%)",VLOOKUP(D22,'Расчет'!$A$2:$AA$20,14,0),IF($E$6="Технологический (Б3=55%)",VLOOKUP(D22,'Расчет'!$A$2:$AA$20,19,0),IF($E$6="Регуляторный (Б4=25%)",VLOOKUP(D22,'Расчет'!$A$2:$AA$20,24,0),VLOOKUP(D22,'Расчет'!$A$2:$AA$20,3,0)))),"") -> 0.3104 | F22: =IFERROR(IF($E$6="Экономический (Б1=50%)",VLOOKUP(D22,'Расчет'!$A$2:$AA$20,15,0),IF($E$6="Технологический (Б3=55%)",VLOOKUP(D22,'Расчет'!$A$2:$AA$20,20,0),IF($E$6="Регуляторный (Б4=25%)",VLOOKUP(D22,'Расчет'!$A$2:$AA$20,25,0),VLOOKUP(D22,'Расчет'!$A$2:$AA$20,4,0)))),"") -> 0.3121 | G22: =IFERROR(IF($E$6="Экономический (Б1=50%)",VLOOKUP(D22,'Расчет'!$A$2:$AA$20,16,0),IF($E$6="Технологический (Б3=55%)",VLOOKUP(D22,'Расчет'!$A$2:$AA$20,21,0),IF($E$6="Регуляторный (Б4=25%)",VLOOKUP(D22,'Расчет'!$A$2:$AA$20,26,0),VLOOKUP(D22,'Расчет'!$A$2:$AA$20,5,0)))),"") -> 0.3164 | I22: Б3 - Цифровизация | J22: =IFERROR(VLOOKUP($J$6,'Расчет'!$A$2:$AA$20,9,0),"") -> 0.5158 | L22: =IFERROR(REPT("█",ROUND(VLOOKUP($J$6,'Расчет'!$A$2:$AA$20,9,0)*10,0)),"") -> █████
B23: 14 | D23: Транспорт и логистика | E23: =IFERROR(IF($E$6="Экономический (Б1=50%)",VLOOKUP(D23,'Расчет'!$A$2:$AA$20,14,0),IF($E$6="Технологический (Б3=55%)",VLOOKUP(D23,'Расчет'!$A$2:$AA$20,19,0),IF($E$6="Регуляторный (Б4=25%)",VLOOKUP(D23,'Расчет'!$A$2:$AA$20,24,0),VLOOKUP(D23,'Расчет'!$A$2:$AA$20,3,0)))),"") -> 0.2523 | F23: =IFERROR(IF($E$6="Экономический (Б1=50%)",VLOOKUP(D23,'Расчет'!$A$2:$AA$20,15,0),IF($E$6="Технологический (Б3=55%)",VLOOKUP(D23,'Расчет'!$A$2:$AA$20,20,0),IF($E$6="Регуляторный (Б4=25%)",VLOOKUP(D23,'Расчет'!$A$2:$AA$20,25,0),VLOOKUP(D23,'Расчет'!$A$2:$AA$20,4,0)))),"") -> 0.2502 | G23: =IFERROR(IF($E$6="Экономический (Б1=50%)",VLOOKUP(D23,'Расчет'!$A$2:$AA$20,16,0),IF($E$6="Технологический (Б3=55%)",VLOOKUP(D23,'Расчет'!$A$2:$AA$20,21,0),IF($E$6="Регуляторный (Б4=25%)",VLOOKUP(D23,'Расчет'!$A$2:$AA$20,26,0),VLOOKUP(D23,'Расчет'!$A$2:$AA$20,5,0)))),"") -> 0.2451 | I23: Б4 - Регуляторика | J23: =IFERROR(VLOOKUP($J$6,'Расчет'!$A$2:$AA$20,10,0),"") -> 0.4509 | L23: =IFERROR(REPT("█",ROUND(VLOOKUP($J$6,'Расчет'!$A$2:$AA$20,10,0)*10,0)),"") -> █████
B24: 15 | D24: Строительство | E24: =IFERROR(IF($E$6="Экономический (Б1=50%)",VLOOKUP(D24,'Расчет'!$A$2:$AA$20,14,0),IF($E$6="Технологический (Б3=55%)",VLOOKUP(D24,'Расчет'!$A$2:$AA$20,19,0),IF($E$6="Регуляторный (Б4=25%)",VLOOKUP(D24,'Расчет'!$A$2:$AA$20,24,0),VLOOKUP(D24,'Расчет'!$A$2:$AA$20,3,0)))),"") -> 0.2594 | F24: =IFERROR(IF($E$6="Экономический (Б1=50%)",VLOOKUP(D24,'Расчет'!$A$2:$AA$20,15,0),IF($E$6="Технологический (Б3=55%)",VLOOKUP(D24,'Расчет'!$A$2:$AA$20,20,0),IF($E$6="Регуляторный (Б4=25%)",VLOOKUP(D24,'Расчет'!$A$2:$AA$20,25,0),VLOOKUP(D24,'Расчет'!$A$2:$AA$20,4,0)))),"") -> 0.258 | G24: =IFERROR(IF($E$6="Экономический (Б1=50%)",VLOOKUP(D24,'Расчет'!$A$2:$AA$20,16,0),IF($E$6="Технологический (Б3=55%)",VLOOKUP(D24,'Расчет'!$A$2:$AA$20,21,0),IF($E$6="Регуляторный (Б4=25%)",VLOOKUP(D24,'Расчет'!$A$2:$AA$20,26,0),VLOOKUP(D24,'Расчет'!$A$2:$AA$20,5,0)))),"") -> 0.2545
B25: 16 | D25: Образование | E25: =IFERROR(IF($E$6="Экономический (Б1=50%)",VLOOKUP(D25,'Расчет'!$A$2:$AA$20,14,0),IF($E$6="Технологический (Б3=55%)",VLOOKUP(D25,'Расчет'!$A$2:$AA$20,19,0),IF($E$6="Регуляторный (Б4=25%)",VLOOKUP(D25,'Расчет'!$A$2:$AA$20,24,0),VLOOKUP(D25,'Расчет'!$A$2:$AA$20,3,0)))),"") -> 0.2268 | F25: =IFERROR(IF($E$6="Экономический (Б1=50%)",VLOOKUP(D25,'Расчет'!$A$2:$AA$20,15,0),IF($E$6="Технологический (Б3=55%)",VLOOKUP(D25,'Расчет'!$A$2:$AA$20,20,0),IF($E$6="Регуляторный (Б4=25%)",VLOOKUP(D25,'Расчет'!$A$2:$AA$20,25,0),VLOOKUP(D25,'Расчет'!$A$2:$AA$20,4,0)))),"") -> 0.2253 | G25: =IFERROR(IF($E$6="Экономический (Б1=50%)",VLOOKUP(D25,'Расчет'!$A$2:$AA$20,16,0),IF($E$6="Технологический (Б3=55%)",VLOOKUP(D25,'Расчет'!$A$2:$AA$20,21,0),IF($E$6="Регуляторный (Б4=25%)",VLOOKUP(D25,'Расчет'!$A$2:$AA$20,26,0),VLOOKUP(D25,'Расчет'!$A$2:$AA$20,5,0)))),"") -> 0.2217 | I25: КЛЮЧЕВЫЕ ФАКТОРЫ
B26: 17 | D26: ЖКХ | E26: =IFERROR(IF($E$6="Экономический (Б1=50%)",VLOOKUP(D26,'Расчет'!$A$2:$AA$20,14,0),IF($E$6="Технологический (Б3=55%)",VLOOKUP(D26,'Расчет'!$A$2:$AA$20,19,0),IF($E$6="Регуляторный (Б4=25%)",VLOOKUP(D26,'Расчет'!$A$2:$AA$20,24,0),VLOOKUP(D26,'Расчет'!$A$2:$AA$20,3,0)))),"") -> 0.2395 | F26: =IFERROR(IF($E$6="Экономический (Б1=50%)",VLOOKUP(D26,'Расчет'!$A$2:$AA$20,15,0),IF($E$6="Технологический (Б3=55%)",VLOOKUP(D26,'Расчет'!$A$2:$AA$20,20,0),IF($E$6="Регуляторный (Б4=25%)",VLOOKUP(D26,'Расчет'!$A$2:$AA$20,25,0),VLOOKUP(D26,'Расчет'!$A$2:$AA$20,4,0)))),"") -> 0.2384 | G26: =IFERROR(IF($E$6="Экономический (Б1=50%)",VLOOKUP(D26,'Расчет'!$A$2:$AA$20,16,0),IF($E$6="Технологический (Б3=55%)",VLOOKUP(D26,'Расчет'!$A$2:$AA$20,21,0),IF($E$6="Регуляторный (Б4=25%)",VLOOKUP(D26,'Расчет'!$A$2:$AA$20,26,0),VLOOKUP(D26,'Расчет'!$A$2:$AA$20,5,0)))),"") -> 0.2358 | I26: =IFERROR(VLOOKUP($J$6,'Расчет'!$A$2:$AA$20,11,0),"") -> ▸ Экономика: 36% ▸ Цифровизация: 52% ▸ Регуляторика: 45%
B27: 18 | D27: ИТ и телекоммуникации | E27: =IFERROR(IF($E$6="Экономический (Б1=50%)",VLOOKUP(D27,'Расчет'!$A$2:$AA$20,14,0),IF($E$6="Технологический (Б3=55%)",VLOOKUP(D27,'Расчет'!$A$2:$AA$20,19,0),IF($E$6="Регуляторный (Б4=25%)",VLOOKUP(D27,'Расчет'!$A$2:$AA$20,24,0),VLOOKUP(D27,'Расчет'!$A$2:$AA$20,3,0)))),"") -> 0.2442 | F27: =IFERROR(IF($E$6="Экономический (Б1=50%)",VLOOKUP(D27,'Расчет'!$A$2:$AA$20,15,0),IF($E$6="Технологический (Б3=55%)",VLOOKUP(D27,'Расчет'!$A$2:$AA$20,20,0),IF($E$6="Регуляторный (Б4=25%)",VLOOKUP(D27,'Расчет'!$A$2:$AA$20,25,0),VLOOKUP(D27,'Расчет'!$A$2:$AA$20,4,0)))),"") -> 0.244 | G27: =IFERROR(IF($E$6="Экономический (Б1=50%)",VLOOKUP(D27,'Расчет'!$A$2:$AA$20,16,0),IF($E$6="Технологический (Б3=55%)",VLOOKUP(D27,'Расчет'!$A$2:$AA$20,21,0),IF($E$6="Регуляторный (Б4=25%)",VLOOKUP(D27,'Расчет'!$A$2:$AA$20,26,0),VLOOKUP(D27,'Расчет'!$A$2:$AA$20,5,0)))),"") -> 0.2437 | I27: =IFERROR(VLOOKUP($J$6,'Расчет'!$A$2:$AA$20,12,0),"") -> → Стабильно
B28: 19 | D28: Энергетика | E28: =IFERROR(IF($E$6="Экономический (Б1=50%)",VLOOKUP(D28,'Расчет'!$A$2:$AA$20,14,0),IF($E$6="Технологический (Б3=55%)",VLOOKUP(D28,'Расчет'!$A$2:$AA$20,19,0),IF($E$6="Регуляторный (Б4=25%)",VLOOKUP(D28,'Расчет'!$A$2:$AA$20,24,0),VLOOKUP(D28,'Расчет'!$A$2:$AA$20,3,0)))),"") -> 0.1784 | F28: =IFERROR(IF($E$6="Экономический (Б1=50%)",VLOOKUP(D28,'Расчет'!$A$2:$AA$20,15,0),IF($E$6="Технологический (Б3=55%)",VLOOKUP(D28,'Расчет'!$A$2:$AA$20,20,0),IF($E$6="Регуляторный (Б4=25%)",VLOOKUP(D28,'Расчет'!$A$2:$AA$20,25,0),VLOOKUP(D28,'Расчет'!$A$2:$AA$20,4,0)))),"") -> 0.1756 | G28: =IFERROR(IF($E$6="Экономический (Б1=50%)",VLOOKUP(D28,'Расчет'!$A$2:$AA$20,16,0),IF($E$6="Технологический (Б3=55%)",VLOOKUP(D28,'Расчет'!$A$2:$AA$20,21,0),IF($E$6="Регуляторный (Б4=25%)",VLOOKUP(D28,'Расчет'!$A$2:$AA$20,26,0),VLOOKUP(D28,'Расчет'!$A$2:$AA$20,5,0)))),"") -> 0.1685
I29: ⚡ Прогноз: линейная экстраполяция тренда SADI 2015–2024
D30: ЛЕГЕНДА
D31: ▓ ВЫСОКИЙ ≥50% | E31: ▒ СРЕДНИЙ 30–50% | F31: ░ НИЗКИЙ <30% | G31: Желтые - ввод

Sheet ➕ Мои критерии
A1: ➕ Мои критерии - добавьте собственные факторы к базовому SADI
A2: Введите название, вес (%) и оценки 1–5 для каждой отрасли. Нормализация считается автоматически. Результат - в листе «🏆 Итог+»
A4: Название: | B4: Критерий 1 | C4: Вес (%) | D4: Критерий 2 | E4: Вес (%) | F4: Критерий 3 | G4: Вес (%) | H4: Критерий 4 | I4: Вес (%) | J4: Критерий 5 | K4: Вес (%)
A5: Вес (%): | B5: ИИ новое | C5: 10 | D5: Мой критерий 2 | E5: 10 | F5: Мой критерий 3 | G5: 10 | H5: Мой критерий 4 | I5: 10 | J5: Мой критерий 5 | K5: 10
A6: Колонки: | B6: Оценка (1–5) | C6: Норм. | D6: Оценка (1–5) | E6: Норм. | F6: Оценка (1–5) | G6: Норм. | H6: Оценка (1–5) | I6: Норм. | J6: Оценка (1–5) | K6: Норм.
A7: Отрасль
A8: Оборонно-промышленный комплекс | B8: 3 | C8: =IFERROR((B8-MIN(B8:B26))/(MAX(B8:B26)-MIN(B8:B26)),0.5) -> 0.5 | D8: 3 | E8: =IFERROR((D8-MIN(D8:D26))/(MAX(D8:D26)-MIN(D8:D26)),0.5) -> 0.5 | F8: 3 | G8: =IFERROR((F8-MIN(F8:F26))/(MAX(F8:F26)-MIN(F8:F26)),0.5) -> 0.5 | H8: 3 | I8: =IFERROR((H8-MIN(H8:H26))/(MAX(H8:H26)-MIN(H8:H26)),0.5) -> 0.5 | J8: 3 | K8: =IFERROR((J8-MIN(J8:J26))/(MAX(J8:J26)-MIN(J8:J26)),0.5) -> 0.5
A9: Нефтегазовый комплекс | B9: 3 | C9: =IFERROR((B9-MIN(B8:B26))/(MAX(B8:B26)-MIN(B8:B26)),0.5) -> 0.5 | D9: 3 | E9: =IFERROR((D9-MIN(D8:D26))/(MAX(D8:D26)-MIN(D8:D26)),0.5) -> 0.5 | F9: 3 | G9: =IFERROR((F9-MIN(F8:F26))/(MAX(F8:F26)-MIN(F8:F26)),0.5) -> 0.5 | H9: 3 | I9: =IFERROR((H9-MIN(H8:H26))/(MAX(H8:H26)-MIN(H8:H26)),0.5) -> 0.5 | J9: 3 | K9: =IFERROR((J9-MIN(J8:J26))/(MAX(J8:J26)-MIN(J8:J26)),0.5) -> 0.5
A10: Финансы и страхование | B10: 3 | C10: =IFERROR((B10-MIN(B8:B26))/(MAX(B8:B26)-MIN(B8:B26)),0.5) -> 0.5 | D10: 3 | E10: =IFERROR((D10-MIN(D8:D26))/(MAX(D8:D26)-MIN(D8:D26)),0.5) -> 0.5 | F10: 3 | G10: =IFERROR((F10-MIN(F8:F26))/(MAX(F8:F26)-MIN(F8:F26)),0.5) -> 0.5 | H10: 3 | I10: =IFERROR((H10-MIN(H8:H26))/(MAX(H8:H26)-MIN(H8:H26)),0.5) -> 0.5 | J10: 3 | K10: =IFERROR((J10-MIN(J8:J26))/(MAX(J8:J26)-MIN(J8:J26)),0.5) -> 0.5
A11: Фармацевтика | B11: 3 | C11: =IFERROR((B11-MIN(B8:B26))/(MAX(B8:B26)-MIN(B8:B26)),0.5) -> 0.5 | D11: 3 | E11: =IFERROR((D11-MIN(D8:D26))/(MAX(D8:D26)-MIN(D8:D26)),0.5) -> 0.5 | F11: 3 | G11: =IFERROR((F11-MIN(F8:F26))/(MAX(F8:F26)-MIN(F8:F26)),0.5) -> 0.5 | H11: 3 | I11: =IFERROR((H11-MIN(H8:H26))/(MAX(H8:H26)-MIN(H8:H26)),0.5) -> 0.5 | J11: 3 | K11: =IFERROR((J11-MIN(J8:J26))/(MAX(J8:J26)-MIN(J8:J26)),0.5) -> 0.5
A12: Обрабатывающая промышленность | B12: 3 | C12: =IFERROR((B12-MIN(B8:B26))/(MAX(B8:B26)-MIN(B8:B26)),0.5) -> 0.5 | D12: 3 | E12: =IFERROR((D12-MIN(D8:D26))/(MAX(D8:D26)-MIN(D8:D26)),0.5) -> 0.5 | F12: 3 | G12: =IFERROR((F12-MIN(F8:F26))/(MAX(F8:F26)-MIN(F8:F26)),0.5) -> 0.5 | H12: 3 | I12: =IFERROR((H12-MIN(H8:H26))/(MAX(H8:H26)-MIN(H8:H26)),0.5) -> 0.5 | J12: 3 | K12: =IFERROR((J12-MIN(J8:J26))/(MAX(J8:J26)-MIN(J8:J26)),0.5) -> 0.5
A13: Металлургия | B13: 3 | C13: =IFERROR((B13-MIN(B8:B26))/(MAX(B8:B26)-MIN(B8:B26)),0.5) -> 0.5 | D13: 3 | E13: =IFERROR((D13-MIN(D8:D26))/(MAX(D8:D26)-MIN(D8:D26)),0.5) -> 0.5 | F13: 3 | G13: =IFERROR((F13-MIN(F8:F26))/(MAX(F8:F26)-MIN(F8:F26)),0.5) -> 0.5 | H13: 3 | I13: =IFERROR((H13-MIN(H8:H26))/(MAX(H8:H26)-MIN(H8:H26)),0.5) -> 0.5 | J13: 3 | K13: =IFERROR((J13-MIN(J8:J26))/(MAX(J8:J26)-MIN(J8:J26)),0.5) -> 0.5
A14: Здравоохранение | B14: 3 | C14: =IFERROR((B14-MIN(B8:B26))/(MAX(B8:B26)-MIN(B8:B26)),0.5) -> 0.5 | D14: 3 | E14: =IFERROR((D14-MIN(D8:D26))/(MAX(D8:D26)-MIN(D8:D26)),0.5) -> 0.5 | F14: 3 | G14: =IFERROR((F14-MIN(F8:F26))/(MAX(F8:F26)-MIN(F8:F26)),0.5) -> 0.5 | H14: 3 | I14: =IFERROR((H14-MIN(H8:H26))/(MAX(H8:H26)-MIN(H8:H26)),0.5) -> 0.5 | J14: 3 | K14: =IFERROR((J14-MIN(J8:J26))/(MAX(J8:J26)-MIN(J8:J26)),0.5) -> 0.5
A15: Торговля | B15: 3 | C15: =IFERROR((B15-MIN(B8:B26))/(MAX(B8:B26)-MIN(B8:B26)),0.5) -> 0.5 | D15: 3 | E15: =IFERROR((D15-MIN(D8:D26))/(MAX(D8:D26)-MIN(D8:D26)),0.5) -> 0.5 | F15: 3 | G15: =IFERROR((F15-MIN(F8:F26))/(MAX(F8:F26)-MIN(F8:F26)),0.5) -> 0.5 | H15: 3 | I15: =IFERROR((H15-MIN(H8:H26))/(MAX(H8:H26)-MIN(H8:H26)),0.5) -> 0.5 | J15: 3 | K15: =IFERROR((J15-MIN(J8:J26))/(MAX(J8:J26)-MIN(J8:J26)),0.5) -> 0.5
A16: Недвижимость | B16: 3 | C16: =IFERROR((B16-MIN(B8:B26))/(MAX(B8:B26)-MIN(B8:B26)),0.5) -> 0.5 | D16: 3 | E16: =IFERROR((D16-MIN(D8:D26))/(MAX(D8:D26)-MIN(D8:D26)),0.5) -> 0.5 | F16: 3 | G16: =IFERROR((F16-MIN(F8:F26))/(MAX(F8:F26)-MIN(F8:F26)),0.5) -> 0.5 | H16: 3 | I16: =IFERROR((H16-MIN(H8:H26))/(MAX(H8:H26)-MIN(H8:H26)),0.5) -> 0.5 | J16: 3 | K16: =IFERROR((J16-MIN(J8:J26))/(MAX(J8:J26)-MIN(J8:J26)),0.5) -> 0.5
A17: Медиа и рекламные технологии | B17: 3 | C17: =IFERROR((B17-MIN(B8:B26))/(MAX(B8:B26)-MIN(B8:B26)),0.5) -> 0.5 | D17: 3 | E17: =IFERROR((D17-MIN(D8:D26))/(MAX(D8:D26)-MIN(D8:D26)),0.5) -> 0.5 | F17: 3 | G17: =IFERROR((F17-MIN(F8:F26))/(MAX(F8:F26)-MIN(F8:F26)),0.5) -> 0.5 | H17: 3 | I17: =IFERROR((H17-MIN(H8:H26))/(MAX(H8:H26)-MIN(H8:H26)),0.5) -> 0.5 | J17: 3 | K17: =IFERROR((J17-MIN(J8:J26))/(MAX(J8:J26)-MIN(J8:J26)),0.5) -> 0.5
A18: Химическая промышленность | B18: 3 | C18: =IFERROR((B18-MIN(B8:B26))/(MAX(B8:B26)-MIN(B8:B26)),0.5) -> 0.5 | D18: 3 | E18: =IFERROR((D18-MIN(D8:D26))/(MAX(D8:D26)-MIN(D8:D26)),0.5) -> 0.5 | F18: 3 | G18: =IFERROR((F18-MIN(F8:F26))/(MAX(F8:F26)-MIN(F8:F26)),0.5) -> 0.5 | H18: 3 | I18: =IFERROR((H18-MIN(H8:H26))/(MAX(H8:H26)-MIN(H8:H26)),0.5) -> 0.5 | J18: 3 | K18: =IFERROR((J18-MIN(J8:J26))/(MAX(J8:J26)-MIN(J8:J26)),0.5) -> 0.5
A19: АПК и пищевая промышленность | B19: 3 | C19: =IFERROR((B19-MIN(B8:B26))/(MAX(B8:B26)-MIN(B8:B26)),0.5) -> 0.5 | D19: 3 | E19: =IFERROR((D19-MIN(D8:D26))/(MAX(D8:D26)-MIN(D8:D26)),0.5) -> 0.5 | F19: 3 | G19: =IFERROR((F19-MIN(F8:F26))/(MAX(F8:F26)-MIN(F8:F26)),0.5) -> 0.5 | H19: 3 | I19: =IFERROR((H19-MIN(H8:H26))/(MAX(H8:H26)-MIN(H8:H26)),0.5) -> 0.5 | J19: 3 | K19: =IFERROR((J19-MIN(J8:J26))/(MAX(J8:J26)-MIN(J8:J26)),0.5) -> 0.5
A20: Туризм и гостеприимство | B20: 3 | C20: =IFERROR((B20-MIN(B8:B26))/(MAX(B8:B26)-MIN(B8:B26)),0.5) -> 0.5 | D20: 3 | E20: =IFERROR((D20-MIN(D8:D26))/(MAX(D8:D26)-MIN(D8:D26)),0.5) -> 0.5 | F20: 3 | G20: =IFERROR((F20-MIN(F8:F26))/(MAX(F8:F26)-MIN(F8:F26)),0.5) -> 0.5 | H20: 3 | I20: =IFERROR((H20-MIN(H8:H26))/(MAX(H8:H26)-MIN(H8:H26)),0.5) -> 0.5 | J20: 3 | K20: =IFERROR((J20-MIN(J8:J26))/(MAX(J8:J26)-MIN(J8:J26)),0.5) -> 0.5
A21: Транспорт и логистика | B21: 3 | C21: =IFERROR((B21-MIN(B8:B26))/(MAX(B8:B26)-MIN(B8:B26)),0.5) -> 0.5 | D21: 3 | E21: =IFERROR((D21-MIN(D8:D26))/(MAX(D8:D26)-MIN(D8:D26)),0.5) -> 0.5 | F21: 3 | G21: =IFERROR((F21-MIN(F8:F26))/(MAX(F8:F26)-MIN(F8:F26)),0.5) -> 0.5 | H21: 3 | I21: =IFERROR((H21-MIN(H8:H26))/(MAX(H8:H26)-MIN(H8:H26)),0.5) -> 0.5 | J21: 3 | K21: =IFERROR((J21-MIN(J8:J26))/(MAX(J8:J26)-MIN(J8:J26)),0.5) -> 0.5
A22: Строительство | B22: 3 | C22: =IFERROR((B22-MIN(B8:B26))/(MAX(B8:B26)-MIN(B8:B26)),0.5) -> 0.5 | D22: 3 | E22: =IFERROR((D22-MIN(D8:D26))/(MAX(D8:D26)-MIN(D8:D26)),0.5) -> 0.5 | F22: 3 | G22: =IFERROR((F22-MIN(F8:F26))/(MAX(F8:F26)-MIN(F8:F26)),0.5) -> 0.5 | H22: 3 | I22: =IFERROR((H22-MIN(H8:H26))/(MAX(H8:H26)-MIN(H8:H26)),0.5) -> 0.5 | J22: 3 | K22: =IFERROR((J22-MIN(J8:J26))/(MAX(J8:J26)-MIN(J8:J26)),0.5) -> 0.5
A23: Образование | B23: 3 | C23: =IFERROR((B23-MIN(B8:B26))/(MAX(B8:B26)-MIN(B8:B26)),0.5) -> 0.5 | D23: 3 | E23: =IFERROR((D23-MIN(D8:D26))/(MAX(D8:D26)-MIN(D8:D26)),0.5) -> 0.5 | F23: 3 | G23: =IFERROR((F23-MIN(F8:F26))/(MAX(F8:F26)-MIN(F8:F26)),0.5) -> 0.5 | H23: 3 | I23: =IFERROR((H23-MIN(H8:H26))/(MAX(H8:H26)-MIN(H8:H26)),0.5) -> 0.5 | J23: 3 | K23: =IFERROR((J23-MIN(J8:J26))/(MAX(J8:J26)-MIN(J8:J26)),0.5) -> 0.5
A24: ЖКХ | B24: 3 | C24: =IFERROR((B24-MIN(B8:B26))/(MAX(B8:B26)-MIN(B8:B26)),0.5) -> 0.5 | D24: 3 | E24: =IFERROR((D24-MIN(D8:D26))/(MAX(D8:D26)-MIN(D8:D26)),0.5) -> 0.5 | F24: 3 | G24: =IFERROR((F24-MIN(F8:F26))/(MAX(F8:F26)-MIN(F8:F26)),0.5) -> 0.5 | H24: 3 | I24: =IFERROR((H24-MIN(H8:H26))/(MAX(H8:H26)-MIN(H8:H26)),0.5) -> 0.5 | J24: 3 | K24: =IFERROR((J24-MIN(J8:J26))/(MAX(J8:J26)-MIN(J8:J26)),0.5) -> 0.5
A25: ИТ и телекоммуникации | B25: 3 | C25: =IFERROR((B25-MIN(B8:B26))/(MAX(B8:B26)-MIN(B8:B26)),0.5) -> 0.5 | D25: 3 | E25: =IFERROR((D25-MIN(D8:D26))/(MAX(D8:D26)-MIN(D8:D26)),0.5) -> 0.5 | F25: 3 | G25: =IFERROR((F25-MIN(F8:F26))/(MAX(F8:F26)-MIN(F8:F26)),0.5) -> 0.5 | H25: 3 | I25: =IFERROR((H25-MIN(H8:H26))/(MAX(H8:H26)-MIN(H8:H26)),0.5) -> 0.5 | J25: 3 | K25: =IFERROR((J25-MIN(J8:J26))/(MAX(J8:J26)-MIN(J8:J26)),0.5) -> 0.5
A26: Энергетика | B26: 3 | C26: =IFERROR((B26-MIN(B8:B26))/(MAX(B8:B26)-MIN(B8:B26)),0.5) -> 0.5 | D26: 3 | E26: =IFERROR((D26-MIN(D8:D26))/(MAX(D8:D26)-MIN(D8:D26)),0.5) -> 0.5 | F26: 3 | G26: =IFERROR((F26-MIN(F8:F26))/(MAX(F8:F26)-MIN(F8:F26)),0.5) -> 0.5 | H26: 3 | I26: =IFERROR((H26-MIN(H8:H26))/(MAX(H8:H26)-MIN(H8:H26)),0.5) -> 0.5 | J26: 3 | K26: =IFERROR((J26-MIN(J8:J26))/(MAX(J8:J26)-MIN(J8:J26)),0.5) -> 0.5
A28: ⚠️ Суммарный вес не более 30%. Результат смотрите в листе «🏆 Итог+»

Sheet 🏆 Итог+
A1: 🏆 Итог+ · SADI (5 лет) + ваши критерии · Расширенный рейтинг
A2: Итог+ = SADI_5лет + вклад критериев 1–5 · Автоматический пересчет при изменении оценок в «➕ Мои критерии»
A5: Ранг | B5: Отрасль | C5: SADI 5л | D5: + Крит.1 | E5: + Крит.2 | F5: + Крит.3 | G5: + Крит.4 | H5: + Крит.5 | I5: ИТОГ+ | J5: Δ ранг | K5: Приоритет
A6: =RANK(I6,I6:I24,0) -> 1 | B6: Оборонно-промышленный комплекс | C6: 0.459 | D6: ='➕ Мои критерии'!C8*'➕ Мои критерии'!C5/100 -> 0.05 | E6: ='➕ Мои критерии'!E8*'➕ Мои критерии'!E5/100 -> 0.05 | F6: ='➕ Мои критерии'!G8*'➕ Мои критерии'!G5/100 -> 0.05 | G6: ='➕ Мои критерии'!I8*'➕ Мои критерии'!I5/100 -> 0.05 | H6: ='➕ Мои критерии'!K8*'➕ Мои критерии'!K5/100 -> 0.05 | I6: =C6+D6+E6+F6+G6+H6 -> 0.709 | J6: =1-RANK(I6,I6:I24,0) -> 0 | K6: =IF(A6<=6,"A — Высокий",IF(A6<=13,"B — Средний","C — Умеренный")) -> A — Высокий
A7: =RANK(I7,I6:I24,0) -> 2 | B7: Нефтегазовый комплекс | C7: 0.4098 | D7: ='➕ Мои критерии'!C9*'➕ Мои критерии'!C5/100 -> 0.05 | E7: ='➕ Мои критерии'!E9*'➕ Мои критерии'!E5/100 -> 0.05 | F7: ='➕ Мои критерии'!G9*'➕ Мои критерии'!G5/100 -> 0.05 | G7: ='➕ Мои критерии'!I9*'➕ Мои критерии'!I5/100 -> 0.05 | H7: ='➕ Мои критерии'!K9*'➕ Мои критерии'!K5/100 -> 0.05 | I7: =C7+D7+E7+F7+G7+H7 -> 0.6598 | J7: =2-RANK(I7,I6:I24,0) -> 0 | K7: =IF(A7<=6,"A — Высокий",IF(A7<=13,"B — Средний","C — Умеренный")) -> A — Высокий
A8: =RANK(I8,I6:I24,0) -> 3 | B8: Финансы и страхование | C8: 0.3954 | D8: ='➕ Мои критерии'!C10*'➕ Мои критерии'!C5/100 -> 0.05 | E8: ='➕ Мои критерии'!E10*'➕ Мои критерии'!E5/100 -> 0.05 | F8: ='➕ Мои критерии'!G10*'➕ Мои критерии'!G5/100 -> 0.05 | G8: ='➕ Мои критерии'!I10*'➕ Мои критерии'!I5/100 -> 0.05 | H8: ='➕ Мои критерии'!K10*'➕ Мои критерии'!K5/100 -> 0.05 | I8: =C8+D8+E8+F8+G8+H8 -> 0.6454 | J8: =3-RANK(I8,I6:I24,0) -> 0 | K8: =IF(A8<=6,"A — Высокий",IF(A8<=13,"B — Средний","C — Умеренный")) -> A — Высокий
A9: =RANK(I9,I6:I24,0) -> 4 | B9: Фармацевтика | C9: 0.3818 | D9: ='➕ Мои критерии'!C11*'➕ Мои критерии'!C5/100 -> 0.05 | E9: ='➕ Мои критерии'!E11*'➕ Мои критерии'!E5/100 -> 0.05 | F9: ='➕ Мои критерии'!G11*'➕ Мои критерии'!G5/100 -> 0.05 | G9: ='➕ Мои критерии'!I11*'➕ Мои критерии'!I5/100 -> 0.05 | H9: ='➕ Мои критерии'!K11*'➕ Мои критерии'!K5/100 -> 0.05 | I9: =C9+D9+E9+F9+G9+H9 -> 0.6318 | J9: =4-RANK(I9,I6:I24,0) -> 0 | K9: =IF(A9<=6,"A — Высокий",IF(A9<=13,"B — Средний","C — Умеренный")) -> A — Высокий
A10: =RANK(I10,I6:I24,0) -> 5 | B10: Обрабатывающая промышленность | C10: 0.367 | D10: ='➕ Мои критерии'!C12*'➕ Мои критерии'!C5/100 -> 0.05 | E10: ='➕ Мои критерии'!E12*'➕ Мои критерии'!E5/100 -> 0.05 | F10: ='➕ Мои критерии'!G12*'➕ Мои критерии'!G5/100 -> 0.05 | G10: ='➕ Мои критерии'!I12*'➕ Мои критерии'!I5/100 -> 0.05 | H10: ='➕ Мои критерии'!K12*'➕ Мои критерии'!K5/100 -> 0.05 | I10: =C10+D10+E10+F10+G10+H10 -> 0.617 | J10: =5-RANK(I10,I6:I24,0) -> 0 | K10: =IF(A10<=6,"A — Высокий",IF(A10<=13,"B — Средний","C — Умеренный")) -> A — Высокий
A11: =RANK(I11,I6:I24,0) -> 6 | B11: Металлургия | C11: 0.3293 | D11: ='➕ Мои критерии'!C13*'➕ Мои критерии'!C5/100 -> 0.05 | E11: ='➕ Мои критерии'!E13*'➕ Мои критерии'!E5/100 -> 0.05 | F11: ='➕ Мои критерии'!G13*'➕ Мои критерии'!G5/100 -> 0.05 | G11: ='➕ Мои критерии'!I13*'➕ Мои критерии'!I5/100 -> 0.05 | H11: ='➕ Мои критерии'!K13*'➕ Мои критерии'!K5/100 -> 0.05 | I11: =C11+D11+E11+F11+G11+H11 -> 0.5793 | J11: =6-RANK(I11,I6:I24,0) -> 0 | K11: =IF(A11<=6,"A — Высокий",IF(A11<=13,"B — Средний","C — Умеренный")) -> A — Высокий
A12: =RANK(I12,I6:I24,0) -> 7 | B12: Здравоохранение | C12: 0.3175 | D12: ='➕ Мои критерии'!C14*'➕ Мои критерии'!C5/100 -> 0.05 | E12: ='➕ Мои критерии'!E14*'➕ Мои критерии'!E5/100 -> 0.05 | F12: ='➕ Мои критерии'!G14*'➕ Мои критерии'!G5/100 -> 0.05 | G12: ='➕ Мои критерии'!I14*'➕ Мои критерии'!I5/100 -> 0.05 | H12: ='➕ Мои критерии'!K14*'➕ Мои критерии'!K5/100 -> 0.05 | I12: =C12+D12+E12+F12+G12+H12 -> 0.5675 | J12: =7-RANK(I12,I6:I24,0) -> 0 | K12: =IF(A12<=6,"A — Высокий",IF(A12<=13,"B — Средний","C — Умеренный")) -> B — Средний
A13: =RANK(I13,I6:I24,0) -> 8 | B13: Торговля | C13: 0.3027 | D13: ='➕ Мои критерии'!C15*'➕ Мои критерии'!C5/100 -> 0.05 | E13: ='➕ Мои критерии'!E15*'➕ Мои критерии'!E5/100 -> 0.05 | F13: ='➕ Мои критерии'!G15*'➕ Мои критерии'!G5/100 -> 0.05 | G13: ='➕ Мои критерии'!I15*'➕ Мои критерии'!I5/100 -> 0.05 | H13: ='➕ Мои критерии'!K15*'➕ Мои критерии'!K5/100 -> 0.05 | I13: =C13+D13+E13+F13+G13+H13 -> 0.5527 | J13: =8-RANK(I13,I6:I24,0) -> 0 | K13: =IF(A13<=6,"A — Высокий",IF(A13<=13,"B — Средний","C — Умеренный")) -> B — Средний
A14: =RANK(I14,I6:I24,0) -> 9 | B14: Недвижимость | C14: 0.2896 | D14: ='➕ Мои критерии'!C16*'➕ Мои критерии'!C5/100 -> 0.05 | E14: ='➕ Мои критерии'!E16*'➕ Мои критерии'!E5/100 -> 0.05 | F14: ='➕ Мои критерии'!G16*'➕ Мои критерии'!G5/100 -> 0.05 | G14: ='➕ Мои критерии'!I16*'➕ Мои критерии'!I5/100 -> 0.05 | H14: ='➕ Мои критерии'!K16*'➕ Мои критерии'!K5/100 -> 0.05 | I14: =C14+D14+E14+F14+G14+H14 -> 0.5396 | J14: =9-RANK(I14,I6:I24,0) -> 0 | K14: =IF(A14<=6,"A — Высокий",IF(A14<=13,"B — Средний","C — Умеренный")) -> B — Средний
A15: =RANK(I15,I6:I24,0) -> 10 | B15: Медиа и рекламные технологии | C15: 0.2836 | D15: ='➕ Мои критерии'!C17*'➕ Мои критерии'!C5/100 -> 0.05 | E15: ='➕ Мои критерии'!E17*'➕ Мои критерии'!E5/100 -> 0.05 | F15: ='➕ Мои критерии'!G17*'➕ Мои критерии'!G5/100 -> 0.05 | G15: ='➕ Мои критерии'!I17*'➕ Мои критерии'!I5/100 -> 0.05 | H15: ='➕ Мои критерии'!K17*'➕ Мои критерии'!K5/100 -> 0.05 | I15: =C15+D15+E15+F15+G15+H15 -> 0.5336 | J15: =10-RANK(I15,I6:I24,0) -> 0 | K15: =IF(A15<=6,"A — Высокий",IF(A15<=13,"B — Средний","C — Умеренный")) -> B — Средний
A16: =RANK(I16,I6:I24,0) -> 12 | B16: Химическая промышленность | C16: 0.27 | D16: ='➕ Мои критерии'!C18*'➕ Мои критерии'!C5/100 -> 0.05 | E16: ='➕ Мои критерии'!E18*'➕ Мои критерии'!E5/100 -> 0.05 | F16: ='➕ Мои критерии'!G18*'➕ Мои критерии'!G5/100 -> 0.05 | G16: ='➕ Мои критерии'!I18*'➕ Мои критерии'!I5/100 -> 0.05 | H16: ='➕ Мои критерии'!K18*'➕ Мои критерии'!K5/100 -> 0.05 | I16: =C16+D16+E16+F16+G16+H16 -> 0.52 | J16: =11-RANK(I16,I6:I24,0) -> -1 | K16: =IF(A16<=6,"A — Высокий",IF(A16<=13,"B — Средний","C — Умеренный")) -> B — Средний
A17: =RANK(I17,I6:I24,0) -> 11 | B17: АПК и пищевая промышленность | C17: 0.2716 | D17: ='➕ Мои критерии'!C19*'➕ Мои критерии'!C5/100 -> 0.05 | E17: ='➕ Мои критерии'!E19*'➕ Мои критерии'!E5/100 -> 0.05 | F17: ='➕ Мои критерии'!G19*'➕ Мои критерии'!G5/100 -> 0.05 | G17: ='➕ Мои критерии'!I19*'➕ Мои критерии'!I5/100 -> 0.05 | H17: ='➕ Мои критерии'!K19*'➕ Мои критерии'!K5/100 -> 0.05 | I17: =C17+D17+E17+F17+G17+H17 -> 0.5216 | J17: =12-RANK(I17,I6:I24,0) -> 1 | K17: =IF(A17<=6,"A — Высокий",IF(A17<=13,"B — Средний","C — Умеренный")) -> B — Средний
A18: =RANK(I18,I6:I24,0) -> 14 | B18: Туризм и гостеприимство | C18: 0.2509 | D18: ='➕ Мои критерии'!C20*'➕ Мои критерии'!C5/100 -> 0.05 | E18: ='➕ Мои критерии'!E20*'➕ Мои критерии'!E5/100 -> 0.05 | F18: ='➕ Мои критерии'!G20*'➕ Мои критерии'!G5/100 -> 0.05 | G18: ='➕ Мои критерии'!I20*'➕ Мои критерии'!I5/100 -> 0.05 | H18: ='➕ Мои критерии'!K20*'➕ Мои критерии'!K5/100 -> 0.05 | I18: =C18+D18+E18+F18+G18+H18 -> 0.5009 | J18: =13-RANK(I18,I6:I24,0) -> -1 | K18: =IF(A18<=6,"A — Высокий",IF(A18<=13,"B — Средний","C — Умеренный")) -> C — Умеренный
A19: =RANK(I19,I6:I24,0) -> 13 | B19: Транспорт и логистика | C19: 0.2512 | D19: ='➕ Мои критерии'!C21*'➕ Мои критерии'!C5/100 -> 0.05 | E19: ='➕ Мои критерии'!E21*'➕ Мои критерии'!E5/100 -> 0.05 | F19: ='➕ Мои критерии'!G21*'➕ Мои критерии'!G5/100 -> 0.05 | G19: ='➕ Мои критерии'!I21*'➕ Мои критерии'!I5/100 -> 0.05 | H19: ='➕ Мои критерии'!K21*'➕ Мои критерии'!K5/100 -> 0.05 | I19: =C19+D19+E19+F19+G19+H19 -> 0.5012 | J19: =14-RANK(I19,I6:I24,0) -> 1 | K19: =IF(A19<=6,"A — Высокий",IF(A19<=13,"B — Средний","C — Умеренный")) -> B — Средний
A20: =RANK(I20,I6:I24,0) -> 15 | B20: Строительство | C20: 0.2491 | D20: ='➕ Мои критерии'!C22*'➕ Мои критерии'!C5/100 -> 0.05 | E20: ='➕ Мои критерии'!E22*'➕ Мои критерии'!E5/100 -> 0.05 | F20: ='➕ Мои критерии'!G22*'➕ Мои критерии'!G5/100 -> 0.05 | G20: ='➕ Мои критерии'!I22*'➕ Мои критерии'!I5/100 -> 0.05 | H20: ='➕ Мои критерии'!K22*'➕ Мои критерии'!K5/100 -> 0.05 | I20: =C20+D20+E20+F20+G20+H20 -> 0.4991 | J20: =15-RANK(I20,I6:I24,0) -> 0 | K20: =IF(A20<=6,"A — Высокий",IF(A20<=13,"B — Средний","C — Умеренный")) -> C — Умеренный
A21: =RANK(I21,I6:I24,0) -> 16 | B21: Образование | C21: 0.2155 | D21: ='➕ Мои критерии'!C23*'➕ Мои критерии'!C5/100 -> 0.05 | E21: ='➕ Мои критерии'!E23*'➕ Мои критерии'!E5/100 -> 0.05 | F21: ='➕ Мои критерии'!G23*'➕ Мои критерии'!G5/100 -> 0.05 | G21: ='➕ Мои критерии'!I23*'➕ Мои критерии'!I5/100 -> 0.05 | H21: ='➕ Мои критерии'!K23*'➕ Мои критерии'!K5/100 -> 0.05 | I21: =C21+D21+E21+F21+G21+H21 -> 0.4655 | J21: =16-RANK(I21,I6:I24,0) -> 0 | K21: =IF(A21<=6,"A — Высокий",IF(A21<=13,"B — Средний","C — Умеренный")) -> C — Умеренный
A22: =RANK(I22,I6:I24,0) -> 17 | B22: ЖКХ | C22: 0.2114 | D22: ='➕ Мои критерии'!C24*'➕ Мои критерии'!C5/100 -> 0.05 | E22: ='➕ Мои критерии'!E24*'➕ Мои критерии'!E5/100 -> 0.05 | F22: ='➕ Мои критерии'!G24*'➕ Мои критерии'!G5/100 -> 0.05 | G22: ='➕ Мои критерии'!I24*'➕ Мои критерии'!I5/100 -> 0.05 | H22: ='➕ Мои критерии'!K24*'➕ Мои критерии'!K5/100 -> 0.05 | I22: =C22+D22+E22+F22+G22+H22 -> 0.4614 | J22: =17-RANK(I22,I6:I24,0) -> 0 | K22: =IF(A22<=6,"A — Высокий",IF(A22<=13,"B — Средний","C — Умеренный")) -> C — Умеренный
A23: =RANK(I23,I6:I24,0) -> 18 | B23: ИТ и телекоммуникации | C23: 0.1923 | D23: ='➕ Мои критерии'!C25*'➕ Мои критерии'!C5/100 -> 0.05 | E23: ='➕ Мои критерии'!E25*'➕ Мои критерии'!E5/100 -> 0.05 | F23: ='➕ Мои критерии'!G25*'➕ Мои критерии'!G5/100 -> 0.05 | G23: ='➕ Мои критерии'!I25*'➕ Мои критерии'!I5/100 -> 0.05 | H23: ='➕ Мои критерии'!K25*'➕ Мои критерии'!K5/100 -> 0.05 | I23: =C23+D23+E23+F23+G23+H23 -> 0.4423 | J23: =18-RANK(I23,I6:I24,0) -> 0 | K23: =IF(A23<=6,"A — Высокий",IF(A23<=13,"B — Средний","C — Умеренный")) -> C — Умеренный
A24: =RANK(I24,I6:I24,0) -> 19 | B24: Энергетика | C24: 0.1836 | D24: ='➕ Мои критерии'!C26*'➕ Мои критерии'!C5/100 -> 0.05 | E24: ='➕ Мои критерии'!E26*'➕ Мои критерии'!E5/100 -> 0.05 | F24: ='➕ Мои критерии'!G26*'➕ Мои критерии'!G5/100 -> 0.05 | G24: ='➕ Мои критерии'!I26*'➕ Мои критерии'!I5/100 -> 0.05 | H24: ='➕ Мои критерии'!K26*'➕ Мои критерии'!K5/100 -> 0.05 | I24: =C24+D24+E24+F24+G24+H24 -> 0.4336 | J24: =19-RANK(I24,I6:I24,0) -> 0 | K24: =IF(A24<=6,"A — Высокий",IF(A24<=13,"B — Средний","C — Умеренный")) -> C — Умеренный

Sheet Расчет
A1: Отрасль | B1: SADI_b | C1: s3_b | D1: s5_b | E1: s10_b | F1: slope_b | G1: B1 | H1: B2 | I1: B3 | J1: B4 | K1: strength | L1: trend | M1: SADI_e | N1: s3_e | O1: s5_e | P1: s10_e | Q1: slope_e | R1: SADI_t | S1: s3_t | T1: s5_t | U1: s10_t | V1: slope_t | W1: SADI_r | X1: s3_r | Y1: s5_r | Z1: s10_r | AA1: slope_r
A2: Оборонно-промышленный комплекс | B2: 0.4655 | C2: 0.4616 | D2: 0.459 | E2: 0.4524 | F2: -0.00132 | G2: 0.3587 | H2: 0.588 | I2: 0.5158 | J2: 0.4509 | K2: ▸ Экономика: 36% ▸ Цифровизация: 52% ▸ Регуляторика: 45% | L2: → Стабильно | M2: 0.4416 | N2: 0.4379 | O2: 0.4354 | P2: 0.4291 | Q2: -0.00125 | R2: 0.4887 | S2: 0.4892 | T2: 0.4895 | U2: 0.4903 | V2: 0.00015 | W2: 0.4747 | X2: 0.4733 | Y2: 0.4724 | Z2: 0.4701 | AA2: -0.00047
A3: Нефтегазовый комплекс | B3: 0.4182 | C3: 0.4132 | D3: 0.4098 | E3: 0.4014 | F3: -0.00168 | G3: 0.2993 | H3: 0.5 | I3: 0.4295 | J3: 0.5642 | K3: ▸ Экономика: 30% ▸ Цифровизация: 43% ▸ Регуляторика: 56% | L3: → Стабильно | M3: 0.3884 | N3: 0.3838 | O3: 0.3806 | P3: 0.3728 | Q3: -0.00156 | R3: 0.4275 | S3: 0.4257 | T3: 0.4245 | U3: 0.4215 | V3: -0.0006 | W3: 0.4447 | X3: 0.4464 | Y3: 0.4476 | Z3: 0.4504 | AA3: 0.00057
A4: Финансы и страхование | B4: 0.4075 | C4: 0.4002 | D4: 0.3954 | E4: 0.3833 | F4: -0.00241 | G4: 0.204 | H4: 0.5258 | I4: 0.4988 | J4: 0.5417 | K4: ▸ Экономика: 20% ▸ Цифровизация: 50% ▸ Регуляторика: 54% | L4: → Стабильно | M4: 0.3597 | N4: 0.3534 | O4: 0.3491 | P4: 0.3384 | Q4: -0.00213 | R4: 0.4482 | S4: 0.4482 | T4: 0.4482 | U4: 0.4481 | V4: -1e-05 | W4: 0.4412 | X4: 0.4424 | Y4: 0.4431 | Z4: 0.4449 | AA4: 0.00037
A5: Фармацевтика | B5: 0.3937 | C5: 0.3866 | D5: 0.3818 | E5: 0.37 | F5: -0.00237 | G5: 0.1987 | H5: 0.2848 | I5: 0.6138 | J5: 0.5537 | K5: ▸ Экономика: 20% ▸ Цифровизация: 61% ▸ Регуляторика: 55% | L5: → Стабильно | M5: 0.3509 | N5: 0.3446 | O5: 0.3403 | P5: 0.3298 | Q5: -0.00211 | R5: 0.4754 | S5: 0.4787 | T5: 0.4808 | U5: 0.4862 | V5: 0.00108 | W5: 0.4292 | X5: 0.4306 | Y5: 0.4315 | Z5: 0.4338 | AA5: 0.00046
A6: Обрабатывающая промышленность | B6: 0.3653 | C6: 0.3663 | D6: 0.367 | E6: 0.3686 | F6: 0.00033 | G6: 0.5454 | H6: 0.0876 | I6: 0.3419 | J6: 0.3622 | K6: ▸ Экономика: 55% ▸ Цифровизация: 34% ▸ Регуляторика: 36% | L6: → Стабильно | M6: 0.4076 | N6: 0.4087 | O6: 0.4094 | P6: 0.4113 | Q6: 0.00037 | R6: 0.3465 | S6: 0.3432 | T6: 0.341 | U6: 0.3355 | V6: -0.0011 | W6: 0.347 | X6: 0.3441 | Y6: 0.3422 | Z6: 0.3374 | AA6: -0.00096
A7: Металлургия | B7: 0.3407 | C7: 0.3339 | D7: 0.3293 | E7: 0.318 | F7: -0.00227 | G7: 0.1674 | H7: 0.2767 | I7: 0.7356 | J7: 0.0405 | K7: ▸ Экономика: 17% ▸ Цифровизация: 74% ▸ Регуляторика: 4% | L7: → Стабильно | M7: 0.3131 | N7: 0.3069 | O7: 0.3027 | P7: 0.2923 | Q7: -0.00208 | R7: 0.4836 | S7: 0.4904 | T7: 0.495 | U7: 0.5064 | V7: 0.00228 | W7: 0.328 | X7: 0.3189 | Y7: 0.3129 | Z7: 0.2978 | AA7: -0.00301
A8: Здравоохранение | B8: 0.3179 | C8: 0.3177 | D8: 0.3175 | E8: 0.3171 | F8: -8e-05 | G8: 0.4868 | H8: 0.0681 | I8: 0.3065 | J8: 0.2798 | K8: ▸ Экономика: 49% ▸ Цифровизация: 31% ▸ Регуляторика: 28% | L8: → Стабильно | M8: 0.3582 | N8: 0.3579 | O8: 0.3577 | P8: 0.3573 | Q8: -9e-05 | R8: 0.3041 | S8: 0.3006 | T8: 0.2983 | U8: 0.2924 | V8: -0.00118 | W8: 0.2972 | X8: 0.2933 | Y8: 0.2907 | Z8: 0.2841 | AA8: -0.00131
A9: Торговля | B9: 0.3036 | C9: 0.303 | D9: 0.3027 | E9: 0.3017 | F9: -0.00019 | G9: 0.4684 | H9: 0.056 | I9: 0.2259 | J9: 0.4049 | K9: ▸ Экономика: 47% ▸ Цифровизация: 23% ▸ Регуляторика: 40% | L9: → Стабильно | M9: 0.3395 | N9: 0.3389 | O9: 0.3385 | P9: 0.3374 | Q9: -0.00021 | R9: 0.2668 | S9: 0.2624 | T9: 0.2595 | U9: 0.2522 | V9: -0.00146 | W9: 0.2973 | X9: 0.2956 | Y9: 0.2944 | Z9: 0.2916 | AA9: -0.00057
A10: Недвижимость | B10: 0.2953 | C10: 0.2919 | D10: 0.2896 | E10: 0.284 | F10: -0.00114 | G10: 0.3075 | H10: 0.0163 | I10: 0.3902 | J10: 0.4492 | K10: ▸ Экономика: 31% ▸ Цифровизация: 39% ▸ Регуляторика: 45% | L10: → Стабильно | M10: 0.2987 | N10: 0.2952 | O10: 0.2929 | P10: 0.2872 | Q10: -0.00115 | R10: 0.3235 | S10: 0.3213 | T10: 0.3199 | U10: 0.3164 | V10: -0.00071 | W10: 0.3095 | X10: 0.3086 | Y10: 0.3079 | Z10: 0.3064 | AA10: -0.00031
A11: Медиа и рекламные технологии | B11: 0.2925 | C11: 0.2872 | D11: 0.2836 | E11: 0.2748 | F11: -0.00177 | G11: 0.1977 | H11: 0.2391 | I11: 0.3674 | J11: 0.4348 | K11: ▸ Экономика: 20% ▸ Цифровизация: 37% ▸ Регуляторика: 43% | L11: → Стабильно | M11: 0.27 | N11: 0.2651 | O11: 0.2619 | P11: 0.2537 | Q11: -0.00163 | R11: 0.321 | S11: 0.3184 | T11: 0.3167 | U11: 0.3125 | V11: -0.00085 | W11: 0.3162 | X11: 0.3149 | Y11: 0.3141 | Z11: 0.312 | AA11: -0.00041
A12: Химическая промышленность | B12: 0.2797 | C12: 0.2739 | D12: 0.27 | E12: 0.2602 | F12: -0.00195 | G12: 0.1511 | H12: 0.1624 | I12: 0.4893 | J12: 0.317 | K12: ▸ Экономика: 15% ▸ Цифровизация: 49% ▸ Регуляторика: 32% | L12: → Стабильно | M12: 0.2539 | N12: 0.2486 | O12: 0.2451 | P12: 0.2362 | Q12: -0.00177 | R12: 0.3554 | S12: 0.3552 | T12: 0.355 | U12: 0.3546 | V12: -8e-05 | W12: 0.2963 | X12: 0.293 | Y12: 0.2909 | Z12: 0.2855 | AA12: -0.00108
A13: АПК и пищевая промышленность | B13: 0.2783 | C13: 0.2743 | D13: 0.2716 | E13: 0.2649 | F13: -0.00134 | G13: 0.259 | H13: 0.0357 | I13: 0.4252 | J13: 0.3532 | K13: ▸ Экономика: 26% ▸ Цифровизация: 43% ▸ Регуляторика: 35% | L13: → Стабильно | M13: 0.2765 | N13: 0.2725 | O13: 0.2698 | P13: 0.2631 | Q13: -0.00133 | R13: 0.3263 | S13: 0.3249 | T13: 0.3239 | U13: 0.3214 | V13: -0.00049 | W13: 0.2878 | X13: 0.2852 | Y13: 0.2835 | Z13: 0.2793 | AA13: -0.00084
... A20: Энергетика | B20: 0.1896 | C20: 0.186 | D20: 0.1836 | E20: 0.1776 | F20: -0.0012 | G20: 0.1837 | H20: 0.1049 | I20: 0.2911 | J20: 0.1136 | K20: ▸ Экономика: 18% ▸ Цифровизация: 29% ▸ Регуляторика: 11% | L20: → Стабильно | M20: 0.1917 | N20: 0.1881 | O20: 0.1856 | P20: 0.1796 | Q20: -0.00121 | R20: 0.2239 | S20: 0.2211 | T20: 0.2192 | U20: 0.2146 | V20: -0.00094 | W20: 0.1826 | X20: 0.1784 | Y20: 0.1756 | Z20: 0.1685 | AA20: -0.00141

Sheet _Списки
A1: Оборонно-промышленный комплекс
A2: Нефтегазовый комплекс
A3: Финансы и страхование
A4: Фармацевтика
A5: Обрабатывающая промышленность
A6: Металлургия
A7: Здравоохранение
A8: Торговля
A9: Недвижимость
A10: Медиа и рекламные технологии
A11: Химическая промышленность
A12: АПК и пищевая промышленность
... A19: Энергетика

Sheet 📂 Данные
A1: 📂 Исходный датасет · 19 отраслей · 2015–2024 · Только для чтения
A2: Идентификация | E2: Блок 1 - Экономика (35%) | I2: Блок 2 - Процессы (20%) | K2: Блок 4 - Регуляторика (15%) | M2: Дополнительно
A3: ID | B3: Отрасль | C3: Блок | D3: Год | E3: ВВП (%) | F3: Инд.Пр-ва | G3: Инвест.(млрд) | H3: Числен.(тыс.) | I3: Зарплата(руб.) | J3: Пр.Труда(%) | K3: Рентаб.(%) | L3: Нал.Нагр.(%) | M3: Убыточн.(%) | N3: Источники
A4: 1 | B4: Нефтегазовый комплекс | C4: 1 | D4: 2015 | E4: 27 | F4: 101.4 | G4: 1080 | H4: 940 | I4: 69500 | J4: 100.4 | K4: 24.4 | L4: 41.5 | M4: - | N4: 1)https://www.eprussia.ru/news/base/2017/9748035.htm 2)https://www.interfax.ru/business/488240 3)https://www.cdu.ru/tek_russia/issue/2024/5/1271/ 4)https://www.m-economy.ru/art.php?nArtId=5632 5)https
A5: 1 | B5: Нефтегазовый комплекс | C5: 1 | D5: 2016 | E5: 22.6 | F5: 102.5 | G5: 1210 | H5: 1006.8 | I5: 85000 | J5: 101.4 | K5: 23.8 | L5: 35.6 | M5: 50 | N5: 1)https://www.eprussia.ru/news/base/2017/9748035.htm 2)https://www.interfax.ru/business/543922 3)https://www.cdu.ru/tek_russia/issue/2024/5/1271/ 4)https://ekam-journal.com/images/2022/2-2022/Gaifulli
A6: 1 | B6: Нефтегазовый комплекс | C6: 1 | D6: 2017 | E6: 16.6 | F6: 99.9 | G6: 1420 | H6: 583.1 | I6: 104000 | J6: 101 | K6: 25.2 | L6: 45.4 | M6: 66.7 | N6: 1)https://ria.ru/20220720/gaz-1803906901.html 2)https://www.cdu.ru/tek_russia/issue/2018/3/471/ 3)https://www.cdu.ru/tek_russia/issue/2024/5/1271/ 4)https://www.spkngk.ru/fileadmin/f/activity/monitori
A7: 1 | B7: Нефтегазовый комплекс | C7: 1 | D7: 2018 | E7: 20.7 | F7: 101.6 | G7: 1380 | H7: 547 | I7: 127000 | J7: 101.5 | K7: 35.3 | L7: 52.5 | M7: 40 | N7: 1)https://ria.ru/20220720/gaz-1803906901.html 2)https://www.cdu.ru/tek_russia/issue/2019/3/586/ 3)https://www.cdu.ru/tek_russia/issue/2024/5/1271/ 4)https://www.spkngk.ru/fileadmin/f/activity/monitori
A8: 1 | B8: Нефтегазовый комплекс | C8: 1 | D8: 2019 | E8: 18.8 | F8: 100.8 | G8: 1330 | H8: 555.6 | I8: 135000 | J8: 101.8 | K8: 31.9 | L8: 50.9 | M8: - | N8: 1)https://ria.ru/20220720/gaz-1803906901.html 2)https://www.interfax.ru/business/690054 3)https://www.cdu.ru/tek_russia/issue/2024/5/1271/ 4)https://www.spkngk.ru/fileadmin/f/activity/monitoring-rynka
A9: 1 | B9: Нефтегазовый комплекс | C9: 1 | D9: 2020 | E9: 13.9 | F9: 91.4 | G9: 1300 | H9: 569.5 | I9: 142000 | J9: 95.1 | K9: 19.8 | L9: 46.5 | M9: 42.9 | N9: 1)https://ria.ru/20220720/gaz-1803906901.html 2)https://www.rbc.ru/economics/02/01/2021/5ff01e859a794777a8796392 3)https://www.cdu.ru/tek_russia/issue/2024/5/1271/ 4)https://www.spkngk.ru/fileadmin/f/
A10: 1 | B10: Нефтегазовый комплекс | C10: 1 | D10: 2021 | E10: 17.4 | F10: 102.2 | G10: 1490 | H10: 585.9 | I10: 149000 | J10: 100.8 | K10: 28.4 | L10: 50.2 | M10: 42.9 | N10: 1)https://rosstat.gov.ru/folder/313/document/174229 2)https://www.interfax.ru/business/813696 3)https://www.cdu.ru/tek_russia/issue/2024/5/1271/ 4)https://www.spkngk.ru/fileadmin/f/activity/monitoring
A11: 1 | B11: Нефтегазовый комплекс | C11: 1 | D11: 2022 | E11: 18.1 | F11: 102 | G11: 1820 | H11: 591.9 | I11: 165000 | J11: 97.5 | K11: 25.9 | L11: 42.2 | M11: 31 | N11: 1)https://rg.ru/2023/04/07/rosstat-vo-vtoroj-ocenke-vvp-za-2022-god-snizil-doliu-neftegazovogo-sektora.html 2)https://www.cdu.ru/tek_russia/articles/1/1118/ 3)https://www.cdu.ru/tek_russia/issue/2024/
A12: 1 | B12: Нефтегазовый комплекс | C12: 1 | D12: 2023 | E12: 16.5 | F12: 99.2 | G12: 2060 | H12: 593.7 | I12: 176000 | J12: 96.4 | K12: 30.2 | L12: 43.5 | M12: 43 | N12: 1)https://www.kommersant.ru/doc/6632852 2)https://morvesti.ru/themes/1694/108219/ 4)https://www.spkngk.ru/fileadmin/f/activity/monitoring-rynka-truda/Monitoring/Monitoring_rynka_truda_v_ngk_2024.pdf 5
A13: 1 | B13: Нефтегазовый комплекс | C13: 1 | D13: 2024 | E13: 11.7 | F13: 96.6 | G13: 2860 | H13: 594.6 | I13: 215500 | J13: 98 | K13: 27.7 | L13: 56.6 | M13: 45.6 | N13: 1)https://strategra.ru/news/tpost/m4a7xx8z91-vvp-rossii-v-2024-godu 2)https://statbase.ru/data/rus-oil-production/ 3)https://www.cdu.ru/tek_russia/issue/2024/5/1271/ 4)https://www.spkngk.ru/fileadmin/
A14: 2 | B14: Металлургия | C14: 1 | D14: 2015 | E14: 4.7 | F14: 97.7 | G14: 110 | H14: - | I14: 33059 | J14: 104 | K14: 22.4 | L14: - | M14: 75 | N14: 1)https://rg.ru/2016/10/02/zapadnye-ogranicheniia-zastavili-otechestvennyh-metallurgov-snizit-ceny.html 2)https://riarating.ru/files/ratings/metallurgy_demo45.pdf 3)https://cyberleninka.ru/article/n/i
A15: 2 | B15: Металлургия | C15: 1 | D15: 2016 | E15: 4.7 | F15: 97.9 | G15: - | H15: - | I15: 35310 | J15: - | K15: 20 | L15: - | M15: 75 | N15: 1)https://s.econf.rae.ru/pdf/2017/05/6225.pdf 2)https://riarating.ru/files/ratings/metallurgy_demo45.pdf 5)https://www.rosstat.gov.ru/labor_market_employment_salaries 7)https://www.consultant.ru/docum
A16: 2 | B16: Металлургия | C16: 1 | D16: 2017 | E16: 5 | F16: 105.2 | G16: 284.5 | H16: 551.7 | I16: 61122 | J16: 104.3 | K16: 50.3 | L16: - | M16: 100 | N16: 1)https://cyberleninka.ru/article/n/statisticheskiy-analiz-deyatelnosti-metallurgicheskogo-sektora/viewer 2)https://riarating.ru/files/ratings/metallurgy_demo45.pdf 3)https://vestnik.utmn.ru/upload/ib
A17: 2 | B17: Металлургия | C17: 1 | D17: 2018 | E17: 5 | F17: 100.6 | G17: 310 | H17: 467.1 | I17: 70721 | J17: 105.1 | K17: 57.3 | L17: - | M17: 33.3 | N17: 1)https://www.kommersant.ru/doc/3947600 2)https://riarating.ru/files/ratings/metallurgy_demo45.pdf 3)https://riarating.ru/industry_newsletters/20190403/630122342.html 4)https://elar.urfu.ru/bitstream/
A18: 2 | B18: Металлургия | C18: 1 | D18: 2019 | E18: 5 | F18: 103.8 | G18: 343 | H18: 455.2 | I18: 78520 | J18: 103 | K18: 66.3 | L18: - | M18: - | N18: 1)https://elar.urfu.ru/bitstream/10995/133910/1/978-5-91256-641-7_2023_159.pdf 2)https://riarating.ru/files/ratings/metallurgy_demo45.pdf 3)https://rg.ru/2019/11/11/investicii-v-predpriiatiia-metallur
A19: 2 | B19: Металлургия | C19: 1 | D19: 2020 | E19: 5 | F19: 97.3 | G19: 336 | H19: 424.1 | I19: 88154 | J19: 104.2 | K19: 81.4 | L19: 3.4 | M19: 50 | N19: 1)https://na-journal.ru/3-2021-ekonomika-menedzhment/3223-statisticheskii-obzor-i-perspektivy-razvitiya-metallurgicheskogo-sektora-na-mirovom-i-rossiiskom-rynkah?ysclid=mpdur3dkht282434602 2)https://r
A20: 2 | B20: Металлургия | C20: 1 | D20: 2021 | E20: 5 | F20: 101.5 | G20: 735 | H20: 424.8 | I20: 96365 | J20: 102.6 | K20: 118 | L20: 4.8 | M20: 30 | N20: 1)https://na-journal.ru/3-2021-ekonomika-menedzhment/3223-statisticheskii-obzor-i-perspektivy-razvitiya-metallurgicheskogo-sektora-na-mirovom-i-rossiiskom-rynkah?ysclid=mpdur3dkht282434602 2)https://r
A21: 2 | B21: Металлургия | C21: 1 | D21: 2022 | E21: 5 | F21: 99.2 | G21: 250 | H21: 436.1 | I21: 108317 | J21: 96.7 | K21: 51.7 | L21: 3.7 | M21: 31 | N21: 1)https://na-journal.ru/3-2021-ekonomika-menedzhment/3223-statisticheskii-obzor-i-perspektivy-razvitiya-metallurgicheskogo-sektora-na-mirovom-i-rossiiskom-rynkah?ysclid=mpdur3dkht282434602 2)https://m
A22: 2 | B22: Металлургия | C22: 1 | D22: 2023 | E22: 5 | F22: 103.7 | G22: 177.3 | H22: 441.4 | I22: 121608 | J22: - | K22: 60.1 | L22: 7 | M22: 28.1 | N22: 1)https://na-journal.ru/3-2021-ekonomika-menedzhment/3223-statisticheskii-obzor-i-perspektivy-razvitiya-metallurgicheskogo-sektora-na-mirovom-i-rossiiskom-rynkah?ysclid=mpdur3dkht282434602 2)https://w
A23: 2 | B23: Металлургия | C23: 1 | D23: 2024 | E23: 5 | F23: 98.8 | G23: 326.4 | H23: 450.5 | I23: 147836 | J23: 104.5 | K23: 71.1 | L23: 5.6 | M23: 27.1 | N23: 1)https://news.rambler.ru/community/53119612-den-21-iyulya-v-istorii/ 2)https://www.tadviser.ru/index.php/Статья:Металлургия_в_России?ysclid=mpdv3tv28v37960996 3)https://www.economy.gov.ru/material/fi
A24: 3 | B24: Химическая промышленность | C24: 1 | D24: 2015 | E24: 1.8 | F24: 106.3 | G24: - | H24: 383.4 | I24: 39342 | J24: 101.2 | K24: 33 | L24: - | M24: 41.4 | N24: 1)https://cyberleninka.ru/article/n/znachimost-himicheskogo-kompleksa-dlya-ekonomiki-rf 2)http://government.ru/info/22664/ 4)https://www.fedstat.ru/indicator/43007 5)https://www.rosstat.gov.ru/labor_m
A25: 3 | B25: Химическая промышленность | C25: 1 | D25: 2016 | E25: 1.21 | F25: 105.3 | G25: 380.5 | H25: 396.2 | I25: 43318 | J25: 100.3 | K25: 24.5 | L25: - | M25: 32.7 | N25: 1)https://ecfor.ru/wp-content/uploads/2019/05/innovatsionnost-kak-faktor-konkurentosposobnosti-himicheskogo-kompleksa-rossii.pdf 2)http://government.ru/info/27207/ 3)https://www.eg-online.ru/article/4
A26: 3 | B26: Химическая промышленность | C26: 1 | D26: 2017 | E26: - | F26: 104.3 | G26: 430 | H26: - | I26: 45894 | J26: 104.2 | K26: 19.8 | L26: - | M26: - | N26: 2)https://www.rccnews.ru/ru/news/plastics/101739/ 3)https://rupec.ru/news/39315/ 5)https://www.rosstat.gov.ru/labor_market_employment_salaries 6)https://www.rosstat.gov.ru/folder/11186 7)https://www.c
A27: 3 | B27: Химическая промышленность | C27: 1 | D27: 2018 | E27: - | F27: 102.7 | G27: 500 | H27: - | I27: 49159 | J27: - | K27: 26.5 | L27: - | M27: 20 | N27: 2)https://www.mrc.ru/news/348437-indeks-himicheskogo-proizvodstva-v-rossii-viros-na-27-percent-v-2018-godu 3)https://ru.ruwiki.ru/wiki/Химическая_промышленность_России 5)https://www.rosstat.gov.ru/lab
A28: 3 | B28: Химическая промышленность | C28: 1 | D28: 2019 | E28: 1.1 | F28: 101.2 | G28: 532.2 | H28: - | I28: 54332 | J28: - | K28: 23.2 | L28: - | M28: 40 | N28: 1)https://www.eg-online.ru/article/408616/ 2)https://web.archive.org/web/20200125045109/https://gks.ru/bgd/free/B04_03/IssWWW.exe/Stg/d05/10.htm 3)http://vestkhimprom.ru/posts/pogovorim-ob-investitsiy
A29: 3 | B29: Химическая промышленность | C29: 1 | D29: 2020 | E29: 1 | F29: 97.1 | G29: - | H29: 365.4 | I29: 57339 | J29: - | K29: 21.6 | L29: 0.6 | M29: - | N29: 1)https://производительность.рф/documents/1587/Итоговый_аналитический_отчет.pdf 2)https://sdelanounas.ru/blogs/139075/ 4)https://www.rosstat.gov.ru/storage/mediabank/Prom_2025.pdf 5)https://www.rossta
A30: 3 | B30: Химическая промышленность | C30: 1 | D30: 2021 | E30: 1.23 | F30: 104.3 | G30: - | H30: 372.1 | I30: 63702 | J30: - | K30: 43 | L30: 3.6 | M30: 20.3 | N30: 1)https://1economic.ru/lib/116946 2)https://rupec.ru/news/46412/?ysclid=mpdxzklo4n790677467 4)https://www.rosstat.gov.ru/storage/mediabank/Prom_2025.pdf 5)https://www.rosstat.gov.ru/labor_market_emplo
A31: 3 | B31: Химическая промышленность | C31: 1 | D31: 2022 | E31: 1.13 | F31: 98.2 | G31: 796 | H31: 378.6 | I31: 75283 | J31: - | K31: 46.7 | L31: 4 | M31: - | N31: 1)https://delprof.ru/press-center/open-analytics/khimicheskaya-otrasl-rossii-2025-transformaciya-vyzovy-i-strategiya-rosta/ 2)https://cyberleninka.ru/article/n/analiz-sovremennogo-sostoyaniya-i-ugroz-
A32: 3 | B32: Химическая промышленность | C32: 1 | D32: 2023 | E32: 1.3 | F32: 101.5 | G32: 900 | H32: 392.4 | I32: 87873 | J32: - | K32: 31.2 | L32: 5.3 | M32: - | N32: 1)https://www.eg-online.ru/article/479800/ 2)https://cyberleninka.ru/article/n/analiz-sovremennogo-sostoyaniya-i-ugroz-razvitiyu-himicheskoy-promyshlennosti-v-kontekste-ekonomicheskoy-bezopasnosti-ros
A33: 3 | B33: Химическая промышленность | C33: 1 | D33: 2024 | E33: 1.1 | F33: 104.2 | G33: 1792.1 | H33: 410.1 | I33: 105835 | J33: 105.8 | K33: 27.6 | L33: 2.9 | M33: 16.5 | N33: 1)https://delprof.ru/press-center/open-analytics/khimicheskaya-otrasl-rossii-2025-transformaciya-vyzovy-i-strategiya-rosta/ 2)https://cyberleninka.ru/article/n/analiz-sovremennogo-sostoyaniya-i-ugroz-
A34: 6 | B34: АПК и пищевая промышленность | C34: 2 | D34: 2015 | E34: 3.87 | F34: 103.7 | G34: 519 | H34: - | I34: 19721 | J34: 102.6 | K34: 21.3 | L34: 3.5 | M34: - | N34: 1) https://statbase.ru/data/rus-agriculture-and-fishing-value-added-share/ 2) https://rosstat.gov.ru/storage/mediabank/Index_proizv_truda%2808102025%29.xlsx 3) https://eec.eaeunion.org/upload/iblock/5
A35: 6 | B35: АПК и пищевая промышленность | C35: 2 | D35: 2016 | E35: 3.84 | F35: 102.2 | G35: 623 | H35: - | I35: 21755 | J35: 104.8 | K35: 16.8 | L35: 3.5 | M35: - | N35: 1) https://statbase.ru/data/rus-agriculture-and-fishing-value-added-share/ 2) https://rosstat.gov.ru/storage/mediabank/Index_proizv_truda%2808102025%29.xlsx 3) https://eec.eaeunion.org/upload/iblock/5
A36: 6 | B36: АПК и пищевая промышленность | C36: 2 | D36: 2017 | E36: 3.55 | F36: 104.6 | G36: 706 | H36: 5078 | I36: 25671 | J36: 102.4 | K36: 17.3 | L36: 4.3 | M36: - | N36: 1) https://statbase.ru/data/rus-agriculture-and-fishing-value-added-share/ 2) https://rosstat.gov.ru/storage/mediabank/Index_proizv_truda%2808102025%29.xlsx 3) https://eec.eaeunion.org/upload/iblock/5
A37: 6 | B37: АПК и пищевая промышленность | C37: 2 | D37: 2018 | E37: 3.39 | F37: 102 | G37: 782 | H37: 4948 | I37: 28699 | J37: 99.8 | K37: 20.2 | L37: 4.1 | M37: - | N37: 1) https://statbase.ru/data/rus-agriculture-and-fishing-value-added-share/ 2) https://rosstat.gov.ru/storage/mediabank/Index_proizv_truda%2808102025%29.xlsx 3) https://eec.eaeunion.org/upload/iblock/5
A38: 6 | B38: АПК и пищевая промышленность | C38: 2 | D38: 2019 | E38: 3.53 | F38: 106 | G38: 839 | H38: 4790 | I38: 31728 | J38: 104.3 | K38: 18.6 | L38: 4.5 | M38: 28.6 | N38: 1) https://statbase.ru/data/rus-agriculture-and-fishing-value-added-share/ 2) https://rosstat.gov.ru/storage/mediabank/Index_proizv_truda%2808102025%29.xlsx 3) https://eec.eaeunion.org/upload/iblock/5
A39: 6 | B39: АПК и пищевая промышленность | C39: 2 | D39: 2020 | E39: 4.01 | F39: 99.8 | G39: 865 | H39: 4645 | I39: 34770 | J39: 101.3 | K39: 22.9 | L39: 3.8 | M39: 27.7 | N39: 1) https://statbase.ru/data/rus-agriculture-and-fishing-value-added-share/ 2) https://rosstat.gov.ru/storage/mediabank/Index_proizv_truda%2808102025%29.xlsx 3) https://eec.eaeunion.org/upload/iblock/5
A40: 6 | B40: АПК и пищевая промышленность | C40: 2 | D40: 2021 | E40: 3.36 | F40: 101.9 | G40: 962 | H40: 4514 | I40: 39437 | J40: 99.6 | K40: 28.9 | L40: 4.7 | M40: 24.6 | N40: 1) https://statbase.ru/data/rus-agriculture-and-fishing-value-added-share/ 2) https://rosstat.gov.ru/storage/mediabank/Index_proizv_truda%2808102025%29.xlsx 3) https://eec.eaeunion.org/upload/iblock/5
A41: 6 | B41: АПК и пищевая промышленность | C41: 2 | D41: 2022 | E41: 3.42 | F41: 108.3 | G41: 1115 | H41: 4495 | I41: 46777 | J41: 110.2 | K41: 21.2 | L41: 4.1 | M41: 24.7 | N41: 1) https://statbase.ru/data/rus-agriculture-and-fishing-value-added-share/ 2) https://rosstat.gov.ru/storage/mediabank/Index_proizv_truda%2808102025%29.xlsx 3) https://eec.eaeunion.org/upload/iblock/5
A42: 6 | B42: АПК и пищевая промышленность | C42: 2 | D42: 2023 | E42: 2.97 | F42: 102.3 | G42: 1252 | H42: 4408 | I42: 65129 | J42: 100.2 | K42: 23.9 | L42: 4.6 | M42: 26.6 | N42: 1) https://statbase.ru/data/rus-agriculture-and-fishing-value-added-share/ 2) https://rosstat.gov.ru/storage/mediabank/Index_proizv_truda%2808102025%29.xlsx 3) https://eec.eaeunion.org/upload/iblock/5
A43: 6 | B43: АПК и пищевая промышленность | C43: 2 | D43: 2024 | E43: 2.74 | F43: 102.7 | G43: 1298 | H43: - | I43: 77735 | J43: 96.8 | K43: 22.4 | L43: 4.9 | M43: 27.3 | N43: 1) https://statbase.ru/data/rus-agriculture-and-fishing-value-added-share/ 2) https://rosstat.gov.ru/storage/mediabank/Index_proizv_truda%2808102025%29.xlsx 3) https://eec.eaeunion.org/upload/iblock/5
A44: 7 | B44: Строительство | C44: 2 | D44: 2015 | E44: 6.2 | F44: 99.9 | G44: 401 | H44: - | I44: 29960 | J44: 96.1 | K44: 5.4 | L44: 12.7 | M44: - | N44: 1) https://www.ra-national.ru/wp-content/uploads/2025/09/nra_stroitelnaja_otrasl_obzor_sentjabr_2025_verst.pdf?ysclid=mpibtyq68640215942 2) https://rosstat.gov.ru/storage/mediabank/Index_proizv_truda%
A45: 7 | B45: Строительство | C45: 2 | D45: 2016 | E45: 6.2 | F45: 101.3 | G45: 443 | H45: - | I45: 32332 | J45: 97.8 | K45: 5.5 | L45: 10.9 | M45: - | N45: 1) https://www.ra-national.ru/wp-content/uploads/2025/09/nra_stroitelnaja_otrasl_obzor_sentjabr_2025_verst.pdf?ysclid=mpibtyq68640215942 2) https://rosstat.gov.ru/storage/mediabank/Index_proizv_truda%
A46: 7 | B46: Строительство | C46: 2 | D46: 2017 | E46: 6 | F46: 97.3 | G46: 511 | H46: 6351 | I46: 33678 | J46: 98.6 | K46: 7.2 | L46: 10.2 | M46: - | N46: 1) https://www.ra-national.ru/wp-content/uploads/2025/09/nra_stroitelnaja_otrasl_obzor_sentjabr_2025_verst.pdf?ysclid=mpibtyq68640215942 2) https://rosstat.gov.ru/storage/mediabank/Index_proizv_truda%
A47: 7 | B47: Строительство | C47: 2 | D47: 2018 | E47: 5.6 | F47: 100.8 | G47: 638 | H47: 6431 | I47: 38518 | J47: 105.6 | K47: 6.1 | L47: 10.4 | M47: - | N47: 1) https://www.ra-national.ru/wp-content/uploads/2025/09/nra_stroitelnaja_otrasl_obzor_sentjabr_2025_verst.pdf?ysclid=mpibtyq68640215942 2) https://rosstat.gov.ru/storage/mediabank/Index_proizv_truda%
A48: 7 | B48: Строительство | C48: 2 | D48: 2019 | E48: 5.5 | F48: 97 | G48: 682 | H48: 6440 | I48: 42630 | J48: 100.6 | K48: 7 | L48: 11.9 | M48: 35.2 | N48: 1) https://www.ra-national.ru/wp-content/uploads/2025/09/nra_stroitelnaja_otrasl_obzor_sentjabr_2025_verst.pdf?ysclid=mpibtyq68640215942 2) https://rosstat.gov.ru/storage/mediabank/Index_proizv_truda%
A49: 7 | B49: Строительство | C49: 2 | D49: 2020 | E49: 5.5 | F49: 99.8 | G49: 745 | H49: 6209 | I49: 44738 | J49: 100.7 | K49: 8.1 | L49: 10.7 | M49: 33.3 | N49: 1) https://www.ra-national.ru/wp-content/uploads/2025/09/nra_stroitelnaja_otrasl_obzor_sentjabr_2025_verst.pdf?ysclid=mpibtyq68640215942 2) https://rosstat.gov.ru/storage/mediabank/Index_proizv_truda%
A50: 7 | B50: Строительство | C50: 2 | D50: 2021 | E50: 4.6 | F50: 100.3 | G50: 907 | H50: 6530 | I50: 51944 | J50: 105.9 | K50: 7.1 | L50: 10.1 | M50: 33.3 | N50: 1) https://www.ra-national.ru/wp-content/uploads/2025/09/nra_stroitelnaja_otrasl_obzor_sentjabr_2025_verst.pdf?ysclid=mpibtyq68640215942 2) https://rosstat.gov.ru/storage/mediabank/Index_proizv_truda%
A51: 7 | B51: Строительство | C51: 2 | D51: 2022 | E51: 4.9 | F51: 103.7 | G51: 1226 | H51: 6605 | I51: 60850 | J51: 105.2 | K51: 9.2 | L51: 11.1 | M51: 30.4 | N51: 1) https://www.ra-national.ru/wp-content/uploads/2025/09/nra_stroitelnaja_otrasl_obzor_sentjabr_2025_verst.pdf?ysclid=mpibtyq68640215942 2) https://rosstat.gov.ru/storage/mediabank/Index_proizv_truda%
A52: 7 | B52: Строительство | C52: 2 | D52: 2023 | E52: 5 | F52: 106 | G52: 1445 | H52: 6814 | I52: 71707 | J52: 107.9 | K52: 10.8 | L52: 13 | M52: 28.3 | N52: 1) https://www.ra-national.ru/wp-content/uploads/2025/09/nra_stroitelnaja_otrasl_obzor_sentjabr_2025_verst.pdf?ysclid=mpibtyq68640215942 2) https://rosstat.gov.ru/storage/mediabank/Index_proizv_truda%
A53: 7 | B53: Строительство | C53: 2 | D53: 2024 | E53: 5 | F53: 102.8 | G53: 1664 | H53: - | I53: 85606 | J53: 102.1 | K53: 9.8 | L53: 14.4 | M53: 29.6 | N53: 1) https://www.ra-national.ru/wp-content/uploads/2025/09/nra_stroitelnaja_otrasl_obzor_sentjabr_2025_verst.pdf?ysclid=mpibtyq68640215942 2) https://rosstat.gov.ru/storage/mediabank/Index_proizv_truda%
A54: 8 | B54: Транспорт и логистика | C54: 2 | D54: 2015 | E54: 6 | F54: 100.3 | G54: 2146.6 | H54: - | I54: 38982 | J54: 99.3 | K54: 10.6 | L54: 7.3 | M54: - | N54: 1) https://rosstat.gov.ru/folder/210/document/13221 2) https://rosstat.gov.ru/storage/mediabank/Index_proizv_truda%2808102025%29.xlsx 3) https://view.officeapps.live.com/op/view.aspx?src=https%3A%2F%2
A55: 8 | B55: Транспорт и логистика | C55: 2 | D55: 2016 | E55: 6.6 | F55: 102.3 | G55: 2424.1 | H55: - | I55: 41510 | J55: 101.6 | K55: 10.8 | L55: 7.2 | M55: - | N55: 1) https://rosstat.gov.ru/folder/210/document/13221 2) https://rosstat.gov.ru/storage/mediabank/Index_proizv_truda%2808102025%29.xlsx 3) https://view.officeapps.live.com/op/view.aspx?src=https%3A%2F%2
A56: 8 | B56: Транспорт и логистика | C56: 2 | D56: 2017 | E56: 6.3 | F56: 100.4 | G56: 2659.4 | H56: 5298 | I56: 43967 | J56: 100.1 | K56: 9.7 | L56: 6.8 | M56: - | N56: 1) https://rosstat.gov.ru/folder/210/document/13221 2) https://rosstat.gov.ru/storage/mediabank/Index_proizv_truda%2808102025%29.xlsx 3) https://view.officeapps.live.com/op/view.aspx?src=https%3A%2F%2
A57: 8 | B57: Транспорт и логистика | C57: 2 | D57: 2018 | E57: 5.9 | F57: 101.6 | G57: 2983 | H57: 5409 | I57: 47474 | J57: 103 | K57: 8.8 | L57: 6.5 | M57: - | N57: 1) https://rosstat.gov.ru/folder/210/document/13221 2) https://rosstat.gov.ru/storage/mediabank/Index_proizv_truda%2808102025%29.xlsx 3) https://view.officeapps.live.com/op/view.aspx?src=https%3A%2F%2
A58: 8 | B58: Транспорт и логистика | C58: 2 | D58: 2019 | E58: 6.2 | F58: 101 | G58: 3315 | H58: 5435 | I58: 51160 | J58: 99.3 | K58: 8.7 | L58: 6.4 | M58: 32.5 | N58: 1) https://rosstat.gov.ru/folder/210/document/13221 2) https://rosstat.gov.ru/storage/mediabank/Index_proizv_truda%2808102025%29.xlsx 3) https://view.officeapps.live.com/op/view.aspx?src=https%3A%2F%2
A59: 8 | B59: Транспорт и логистика | C59: 2 | D59: 2020 | E59: 5.8 | F59: 89.9 | G59: 3138.6 | H59: 5490 | I59: 52939 | J59: 102.4 | K59: 3.4 | L59: 6 | M59: 37.4 | N59: 1) https://rosstat.gov.ru/folder/210/document/13221 2) https://rosstat.gov.ru/storage/mediabank/Index_proizv_truda%2808102025%29.xlsx 3) https://view.officeapps.live.com/op/view.aspx?src=https%3A%2F%2
A60: 8 | B60: Транспорт и логистика | C60: 2 | D60: 2021 | E60: 5.6 | F60: 103.2 | G60: 3837.4 | H60: 5691 | I60: 58391 | J60: 100 | K60: 8 | L60: 6 | M60: 30.4 | N60: 1) https://rosstat.gov.ru/folder/210/document/13221 2) https://rosstat.gov.ru/storage/mediabank/Index_proizv_truda%2808102025%29.xlsx 3) https://view.officeapps.live.com/op/view.aspx?src=https%3A%2F%2
A61: 8 | B61: Транспорт и логистика | C61: 2 | D61: 2022 | E61: 6 | F61: 98 | G61: 5152.9 | H61: 5805 | I61: 66926 | J61: 102 | K61: 10.7 | L61: 5.3 | M61: 32.1 | N61: 1) https://rosstat.gov.ru/folder/210/document/13221 2) https://rosstat.gov.ru/storage/mediabank/Index_proizv_truda%2808102025%29.xlsx 3) https://view.officeapps.live.com/op/view.aspx?src=https%3A%2F%2
A62: 8 | B62: Транспорт и логистика | C62: 2 | D62: 2023 | E62: 6 | F62: 101.3 | G62: 6164 | H62: 5899 | I62: 76223 | J62: 100.4 | K62: 15.1 | L62: 7 | M62: 29.9 | N62: 1) https://rosstat.gov.ru/folder/210/document/13221 2) https://rosstat.gov.ru/storage/mediabank/Index_proizv_truda%2808102025%29.xlsx 3) https://view.officeapps.live.com/op/view.aspx?src=https%3A%2F%2
A63: 8 | B63: Транспорт и логистика | C63: 2 | D63: 2024 | E63: 6.1 | F63: 100.3 | G63: 6859.7 | H63: - | I63: 90120 | J63: 100.2 | K63: 13 | L63: 6 | M63: 31.5 | N63: 1) https://rosstat.gov.ru/folder/210/document/13221 2) https://rosstat.gov.ru/storage/mediabank/Index_proizv_truda%2808102025%29.xlsx 3) https://view.officeapps.live.com/op/view.aspx?src=https%3A%2F%2
A64: 9 | B64: Торговля | C64: 2 | D64: 2015 | E64: 14.2 | F64: 93 | G64: 542.7 | H64: - | I64: 26947 | J64: 91.7 | K64: 7.1 | L64: 2.7 | M64: - | N64: 1) https://rosstat.gov.ru/folder/210/document/13221 2) https://rosstat.gov.ru/storage/mediabank/Index_proizv_truda%2808102025%29.xlsx 3) https://view.officeapps.live.com/op/view.aspx?src=https%3A%2F%2
A65: 9 | B65: Торговля | C65: 2 | D65: 2016 | E65: 13.2 | F65: 96.5 | G65: 637 | H65: - | I65: 30030 | J65: 98.6 | K65: 5.3 | L65: 2.8 | M65: - | N65: 1) https://rosstat.gov.ru/folder/210/document/13221 2) https://rosstat.gov.ru/storage/mediabank/Index_proizv_truda%2808102025%29.xlsx 3) https://view.officeapps.live.com/op/view.aspx?src=https%3A%2F%2
A66: 9 | B66: Торговля | C66: 2 | D66: 2017 | E66: 12.8 | F66: 100.4 | G66: 647.2 | H66: 13726 | I66: 32093 | J66: 103.8 | K66: 4.6 | L66: 3.2 | M66: - | N66: 1) https://rosstat.gov.ru/folder/210/document/13221 2) https://rosstat.gov.ru/storage/mediabank/Index_proizv_truda%2808102025%29.xlsx 3) https://view.officeapps.live.com/op/view.aspx?src=https%3A%2F%2
A67: 9 | B67: Торговля | C67: 2 | D67: 2018 | E67: 12 | F67: 101.7 | G67: 784.1 | H67: 13728 | I67: 35444 | J67: 103.9 | K67: 7.3 | L67: 2.9 | M67: - | N67: 1) https://rosstat.gov.ru/folder/210/document/13221 2) https://rosstat.gov.ru/storage/mediabank/Index_proizv_truda%2808102025%29.xlsx 3) https://view.officeapps.live.com/op/view.aspx?src=https%3A%2F%2
A68: 9 | B68: Торговля | C68: 2 | D68: 2019 | E68: 11.6 | F68: 93.2 | G68: 723.9 | H68: 13570 | I68: 40137 | J68: 101.5 | K68: 6.4 | L68: 2.8 | M68: 24.6 | N68: 1) https://rosstat.gov.ru/folder/210/document/13221 2) https://rosstat.gov.ru/storage/mediabank/Index_proizv_truda%2808102025%29.xlsx 3) https://view.officeapps.live.com/op/view.aspx?src=https%3A%2F%2
A69: 9 | B69: Торговля | C69: 2 | D69: 2020 | E69: 11 | F69: 96.1 | G69: 683 | H69: 13133 | I69: 41867 | J69: 96.7 | K69: 5.1 | L69: 3 | M69: 24.4 | N69: 1) https://rosstat.gov.ru/folder/210/document/13221 2) https://rosstat.gov.ru/storage/mediabank/Index_proizv_truda%2808102025%29.xlsx 3) https://view.officeapps.live.com/op/view.aspx?src=https%3A%2F%2
A70: 9 | B70: Торговля | C70: 2 | D70: 2021 | E70: 12 | F70: 101.1 | G70: 1003.6 | H70: 13357 | I70: 50389 | J70: 106.9 | K70: 8.8 | L70: 2.8 | M70: 19.9 | N70: 1) https://rosstat.gov.ru/folder/210/document/13221 2) https://rosstat.gov.ru/storage/mediabank/Index_proizv_truda%2808102025%29.xlsx 3) https://view.officeapps.live.com/op/view.aspx?src=https%3A%2F%2
A71: 9 | B71: Торговля | C71: 2 | D71: 2022 | E71: 12.6 | F71: 102.1 | G71: 1057.9 | H71: 13383 | I71: 57806 | J71: 95 | K71: 9.4 | L71: 3.7 | M71: 20.1 | N71: 1) https://rosstat.gov.ru/folder/210/document/13221 2) https://rosstat.gov.ru/storage/mediabank/Index_proizv_truda%2808102025%29.xlsx 3) https://view.officeapps.live.com/op/view.aspx?src=https%3A%2F%2
A72: 9 | B72: Торговля | C72: 2 | D72: 2023 | E72: 11.5 | F72: 101.4 | G72: 1199.3 | H72: 13391 | I72: 66226 | J72: 107.2 | K72: 5.6 | L72: 4.1 | M72: 21.3 | N72: 1) https://rosstat.gov.ru/folder/210/document/13221 2) https://rosstat.gov.ru/storage/mediabank/Index_proizv_truda%2808102025%29.xlsx 3) https://view.officeapps.live.com/op/view.aspx?src=https%3A%2F%2
A73: 9 | B73: Торговля | C73: 2 | D73: 2024 | E73: 10.9 | F73: 100.9 | G73: 1375.6 | H73: - | I73: 77184 | J73: 105.8 | K73: 4.9 | L73: 3.4 | M73: 21.5 | N73: 1) https://rosstat.gov.ru/folder/210/document/13221 2) https://rosstat.gov.ru/storage/mediabank/Index_proizv_truda%2808102025%29.xlsx 3) https://view.officeapps.live.com/op/view.aspx?src=https%3A%2F%2
A74: 11 | B74: Здравоохранение | C74: 2 | D74: 2015 | E74: 3.11 | F74: 101.3 | G74: 13900 | H74: 4150 | I74: 29239 | J74: 98.6 | K74: 8.3 | L74: 2.06 | M74: 32.6 | N74: 1. https://statbase.ru/data/rus-health-expenditure-gdp-share/ 2. https://www.iep.ru/files/text/trends/2025/book_2024.pdf 3. https://statbase.ru/datasets/national-statistics-of-russia/finance-taxes-b
A75: 11 | B75: Здравоохранение | C75: 2 | D75: 2016 | E75: 3.01 | F75: 102.1 | G75: 14750 | H75: 4150 | I75: 30876 | J75: 100 | K75: 8.4 | L75: 1.72 | M75: 26 | N75: 1. https://statbase.ru/data/rus-health-expenditure-gdp-share/ 2. https://www.iep.ru/files/text/trends/2025/book_2024.pdf 3. https://statbase.ru/datasets/national-statistics-of-russia/finance-taxes-b
A76: 11 | B76: Здравоохранение | C76: 2 | D76: 2017 | E76: 3.06 | F76: 102.4 | G76: 16030 | H76: 4150 | I76: 32965 | J76: 102 | K76: 9.1 | L76: 1.47 | M76: 31.9 | N76: 1. https://statbase.ru/data/rus-health-expenditure-gdp-share/ 2. https://www.iep.ru/files/text/trends/2025/book_2024.pdf 3. https://statbase.ru/datasets/national-statistics-of-russia/finance-taxes-b
A77: 11 | B77: Здравоохранение | C77: 2 | D77: 2018 | E77: 3.18 | F77: 102.8 | G77: 17780 | H77: 4200 | I77: 41384 | J77: 103 | K77: 9.1 | L77: 1.16 | M77: 27.4 | N77: 1. https://statbase.ru/data/rus-health-expenditure-gdp-share/ 2. https://www.iep.ru/files/text/trends/2025/book_2024.pdf 3. https://statbase.ru/datasets/national-statistics-of-russia/finance-taxes-b
A78: 11 | B78: Здравоохранение | C78: 2 | D78: 2019 | E78: 3.45 | F78: 103.2 | G78: 19330 | H78: 4180 | I78: 44586 | J78: 102.4 | K78: 9.5 | L78: 0.81 | M78: 28.4 | N78: 1. https://statbase.ru/data/rus-health-expenditure-gdp-share/ 2. https://www.iep.ru/files/text/trends/2025/book_2024.pdf 3. https://statbase.ru/datasets/national-statistics-of-russia/finance-taxes-b
A79: 11 | B79: Здравоохранение | C79: 2 | D79: 2020 | E79: 5.92 | F79: 104.5 | G79: 20390 | H79: 4180 | I79: 51266 | J79: 99.5 | K79: 9.5 | L79: 1.03 | M79: 35.2 | N79: 1. https://statbase.ru/data/rus-health-expenditure-gdp-share/ 2. https://www.iep.ru/files/text/trends/2025/book_2024.pdf 3. https://statbase.ru/datasets/national-statistics-of-russia/finance-taxes-b
A80: 11 | B80: Здравоохранение | C80: 2 | D80: 2021 | E80: 4.85 | F80: 105.8 | G80: 23240 | H80: 4190 | I80: 52535 | J80: 103.9 | K80: 10.8 | L80: 1.1 | M80: 31 | N80: 1. https://statbase.ru/data/rus-health-expenditure-gdp-share/ 2. https://www.iep.ru/files/text/trends/2025/book_2024.pdf 3. https://statbase.ru/datasets/national-statistics-of-russia/finance-taxes-b
A81: 11 | B81: Здравоохранение | C81: 2 | D81: 2022 | E81: 4.89 | F81: 98.4 | G81: 28410 | H81: 4136.2 | I81: 57460 | J81: 97.1 | K81: 10 | L81: 1.2 | M81: 32.8 | N81: 1. https://statbase.ru/data/rus-health-expenditure-gdp-share/ 2. https://www.iep.ru/files/text/trends/2025/book_2024.pdf 3. https://statbase.ru/datasets/national-statistics-of-russia/finance-taxes-b
A82: 11 | B82: Здравоохранение | C82: 2 | D82: 2023 | E82: 3.5 | F82: 101.2 | G82: 34040 | H82: 4095.3 | I82: 63880 | J82: 102.4 | K82: 10.8 | L82: 1.08 | M82: 24.7 | N82: 1. https://www.vshouz.ru/upload/iblock/aa0/vt1ah5z683vqoulek7p8ykcr3sd6nf83/BYUDZHET-ZDRAV-2025_-2027_zaklyuchenie_06-10-2024_-_2_.pdf 2. https://www.iep.ru/files/text/trends/2025/book_2024.pd
A83: 11 | B83: Здравоохранение | C83: 2 | D83: 2024 | E83: 3.5 | F83: 102.6 | G83: 39920 | H83: 4093.8 | I83: 74585 | J83: 103.4 | K83: 10.8 | L83: 0.74 | M83: 25.5 | N83: 1. https://www.vshouz.ru/upload/iblock/aa0/vt1ah5z683vqoulek7p8ykcr3sd6nf83/BYUDZHET-ZDRAV-2025_-2027_zaklyuchenie_06-10-2024_-_2_.pdf 2. https://www.iep.ru/files/text/trends/2025/book_2024.pd
A84: 12 | B84: Образование | C84: 2 | D84: 2015 | E84: 3.83 | F84: 99.1 | G84: 241 | H84: 5683 | I84: 26920 | J84: 98.4 | K84: 6.9 | L84: 5.9 | M84: 26.1 | N84: 1. https://statbase.ru/data/rus-education-expenditure-share-of-gdp/ 2. https://businesstat.ru/images/demo/commercial_higher_education_russia_demo_businesstat.pdf https://rosstat.gov.ru/folder/313/do
A85: 12 | B85: Образование | C85: 2 | D85: 2016 | E85: 3.76 | F85: 99.4 | G85: 210.5 | H85: 5655 | I85: 28088 | J85: 99.1 | K85: 7.2 | L85: 5.5 | M85: 27.4 | N85: 1. https://statbase.ru/data/rus-education-expenditure-share-of-gdp/ 2. https://businesstat.ru/images/demo/commercial_higher_education_russia_demo_businesstat.pdf https://rosstat.gov.ru/folder/313/do
... A103: 13 | B103: ИТ и телекоммуникации | C103: 3 | D103: 2024 | E103: 3.9 | F103: 63.1 | G103: 1500 | H103: 1540 | I103: 163531 | J103: 107.8 | K103: 15.4 | L103: 14.5 | M103: 28 | N103: 1. https://www.tadviser.ru/index.php/Статья:_ИТ-рынок_России https://economy.gov.ru/material/file/450ce3f2da1ecf8a6ec8f4e9fd0cbdd3/Prognoz2024.pdf https://www.hse.ru/mirror/pubs/share/892396113.pdf
A104: 14 | B104: Финансы и страхование | C104: 3 | D104: 2015 | E104: 4 | F104: 94.8 | G104: 172.1 | H104: 1346 | I104: 70088 | J104: 104.1 | K104: - | L104: 0.5 | M104: 37.3 | N104: 1. https://cyberleninka.ru/article/n/finansovyy-sektor-ekonomiki-dinamika-i-faktory-razvitiya 2. https://cyberleninka.ru/article/n/issledovanie-strategicheskih-prioritetov-i-strukturnoy-transformatsi
A105: 14 | B105: Финансы и страхование | C105: 3 | D105: 2016 | E105: 4.2 | F105: 102.9 | G105: 156 | H105: 1332 | I105: 80289 | J105: 101.8 | K105: - | L105: 0.5 | M105: 33.8 | N105: 1. https://cyberleninka.ru/article/n/finansovyy-sektor-ekonomiki-dinamika-i-faktory-razvitiya 2. https://cyberleninka.ru/article/n/issledovanie-strategicheskih-prioritetov-i-strukturnoy-transformatsi
A106: 14 | B106: Финансы и страхование | C106: 3 | D106: 2017 | E106: 4.1 | F106: 103.4 | G106: 163.3 | H106: 1329 | I106: 84904 | J106: 105.2 | K106: 0.4 | L106: 0.4 | M106: 24.7 | N106: 1. https://cyberleninka.ru/article/n/finansovyy-sektor-ekonomiki-dinamika-i-faktory-razvitiya 2. https://cyberleninka.ru/article/n/issledovanie-strategicheskih-prioritetov-i-strukturnoy-transformatsi
A107: 14 | B107: Финансы и страхование | C107: 3 | D107: 2018 | E107: 3.9 | F107: 106.1 | G107: 233.4 | H107: 1327 | I107: 91070 | J107: 104.8 | K107: - | L107: 26.9 | M107: 24.6 | N107: 1. https://cyberleninka.ru/article/n/finansovyy-sektor-ekonomiki-dinamika-i-faktory-razvitiya 2. https://cyberleninka.ru/article/n/issledovanie-strategicheskih-prioritetov-i-strukturnoy-transformatsi
A108: 14 | B108: Финансы и страхование | C108: 3 | D108: 2019 | E108: 3.8 | F108: 101.3 | G108: 291 | H108: 1319 | I108: 103668 | J108: 108.7 | K108: - | L108: 22.7 | M108: 20 | N108: 1. https://cyberleninka.ru/article/n/finansovyy-sektor-ekonomiki-dinamika-i-faktory-razvitiya 2. https://cyberleninka.ru/article/n/issledovanie-strategicheskih-prioritetov-i-strukturnoy-transformatsi
A109: 14 | B109: Финансы и страхование | C109: 3 | D109: 2020 | E109: 4.5 | F109: 107.3 | G109: 315.3 | H109: 1311 | I109: 112680 | J109: 115.6 | K109: - | L109: 24 | M109: 23.7 | N109: 1. https://cyberleninka.ru/article/n/finansovyy-sektor-ekonomiki-dinamika-i-faktory-razvitiya 2. https://cyberleninka.ru/article/n/issledovanie-strategicheskih-prioritetov-i-strukturnoy-transformatsi
A110: 14 | B110: Финансы и страхование | C110: 3 | D110: 2021 | E110: 4.7 | F110: 111.2 | G110: 374.2 | H110: 1315 | I110: 130223 | J110: 112.6 | K110: 29.9 | L110: 23.2 | M110: 23.8 | N110: 1. https://cyberleninka.ru/article/n/finansovyy-sektor-ekonomiki-dinamika-i-faktory-razvitiya 2. https://cyberleninka.ru/article/n/issledovanie-strategicheskih-prioritetov-i-strukturnoy-transformatsi
A111: 14 | B111: Финансы и страхование | C111: 3 | D111: 2022 | E111: 5.3 | F111: 102.4 | G111: 456.2 | H111: 1305 | I111: 146637 | J111: 115.3 | K111: 34.7 | L111: 43.4 | M111: 24.8 | N111: 1. https://cyberleninka.ru/article/n/finansovyy-sektor-ekonomiki-dinamika-i-faktory-razvitiya 2. https://cyberleninka.ru/article/n/issledovanie-strategicheskih-prioritetov-i-strukturnoy-transformatsi
A112: 14 | B112: Финансы и страхование | C112: 3 | D112: 2023 | E112: 4.6 | F112: 108.6 | G112: 551.4 | H112: 1276 | I112: 170600 | J112: 108.6 | K112: 30 | L112: 30 | M112: 23 | N112: 1. https://cyberleninka.ru/article/n/finansovyy-sektor-ekonomiki-dinamika-i-faktory-razvitiya 2. https://cyberleninka.ru/article/n/issledovanie-strategicheskih-prioritetov-i-strukturnoy-transformatsi
A113: 14 | B113: Финансы и страхование | C113: 3 | D113: 2024 | E113: 5 | F113: 104.3 | G113: 689.8 | H113: 1269 | I113: 205974 | J113: 106.7 | K113: 45.8 | L113: 27.8 | M113: 19.5 | N113: 1. https://cyberleninka.ru/article/n/finansovyy-sektor-ekonomiki-dinamika-i-faktory-razvitiya 2. https://cyberleninka.ru/article/n/issledovanie-strategicheskih-prioritetov-i-strukturnoy-transformatsi
A114: 15 | B114: Медиа и рекламные технологии | C114: 3 | D114: 2015 | E114: 0.37 | F114: 90 | G114: - | H114: 96 | I114: 50200 | J114: 98.9 | K114: 2.3 | L114: 9.7 | M114: 23 | N114: 1. https://www.tadviser.ru/index.php/Статья:Реклама_%28рынок_России%29 https://delprof.ru/press-center/open-analytics/reklamnyj-rynok-rossii/ 2. https://www.vedomosti.ru/media/articles/2025/03/27/11
A115: 15 | B115: Медиа и рекламные технологии | C115: 3 | D115: 2016 | E115: 0.42 | F115: 111 | G115: - | H115: 98 | I115: 53400 | J115: 100.2 | K115: 4.6 | L115: 9.6 | M115: 23 | N115: 1. https://www.tadviser.ru/index.php/Статья:Реклама_%28рынок_России%29 https://delprof.ru/press-center/open-analytics/reklamnyj-rynok-rossii/ 2. https://www.vedomosti.ru/media/articles/2025/03/27/11
A116: 15 | B116: Медиа и рекламные технологии | C116: 3 | D116: 2017 | E116: 0.45 | F116: 114 | G116: 769.7 | H116: 102 | I116: 56958 | J116: 101.9 | K116: 4 | L116: 10.8 | M116: 24 | N116: 1. https://www.tadviser.ru/index.php/Статья:Реклама_%28рынок_России%29 https://delprof.ru/press-center/open-analytics/reklamnyj-rynok-rossii/ 2. https://www.vedomosti.ru/media/articles/2025/03/27/11
A117: 15 | B117: Медиа и рекламные технологии | C117: 3 | D117: 2018 | E117: 0.45 | F117: 112 | G117: 872.4 | H117: 105 | I117: 67509 | J117: 103.2 | K117: 4 | L117: 11 | M117: 26 | N117: 1. https://www.tadviser.ru/index.php/Статья:Реклама_%28рынок_России%29 https://delprof.ru/press-center/open-analytics/reklamnyj-rynok-rossii/ 2. https://www.vedomosti.ru/media/articles/2025/03/27/11
...
